{
  "id": "ecard3",
  "name": "Skyridge",
  "shortName": "Skyridge",
  "serie": "E-Card",
  "releaseYear": 2003,
  "releaseDate": "2003-05-12",
  "cardCount": 182,
  "officialCount": 144,
  "ligaSetCode": "SK",
  "tcgdexSetId": "ecard3",
  "logoUrl": "https://assets.tcgdex.net/en/ecard/ecard3/logo",
  "symbolUrl": "https://assets.tcgdex.net/univ/ecard/ecard3/symbol",
  "language": "en",
  "hasPortugueseData": false,
  "cards": [
    {
      "id": "ecard3-1",
      "name": "Aerodactyl",
      "searchName": "Aerodactyl",
      "collectionId": "ecard3",
      "collectionName": "Skyridge",
      "ligaSetCode": "SK",
      "tcgdexSetId": "ecard3",
      "number": "1",
      "printedTotal": "144",
      "imageUrl": "https://assets.tcgdex.net/en/ecard/ecard3/1",
      "types": [],
      "rarity": ""
    },
    {
      "id": "ecard3-2",
      "name": "Alakazam",
      "searchName": "Alakazam",
      "collectionId": "ecard3",
      "collectionName": "Skyridge",
      "ligaSetCode": "SK",
      "tcgdexSetId": "ecard3",
      "number": "2",
      "printedTotal": "144",
      "imageUrl": "https://assets.tcgdex.net/en/ecard/ecard3/2",
      "types": [],
      "rarity": ""
    },
    {
      "id": "ecard3-3",
      "name": "Arcanine",
      "searchName": "Arcanine",
      "collectionId": "ecard3",
      "collectionName": "Skyridge",
      "ligaSetCode": "SK",
      "tcgdexSetId": "ecard3",
      "number": "3",
      "printedTotal": "144",
      "imageUrl": "https://assets.tcgdex.net/en/ecard/ecard3/3",
      "types": [],
      "rarity": ""
    },
    {
      "id": "ecard3-4",
      "name": "Articuno",
      "searchName": "Articuno",
      "collectionId": "ecard3",
      "collectionName": "Skyridge",
      "ligaSetCode": "SK",
      "tcgdexSetId": "ecard3",
      "number": "4",
      "printedTotal": "144",
      "imageUrl": "https://assets.tcgdex.net/en/ecard/ecard3/4",
      "types": [],
      "rarity": ""
    },
    {
      "id": "ecard3-5",
      "name": "Beedrill",
      "searchName": "Beedrill",
      "collectionId": "ecard3",
      "collectionName": "Skyridge",
      "ligaSetCode": "SK",
      "tcgdexSetId": "ecard3",
      "number": "5",
      "printedTotal": "144",
      "imageUrl": "https://assets.tcgdex.net/en/ecard/ecard3/5",
      "types": [],
      "rarity": ""
    },
    {
      "id": "ecard3-6",
      "name": "Crobat",
      "searchName": "Crobat",
      "collectionId": "ecard3",
      "collectionName": "Skyridge",
      "ligaSetCode": "SK",
      "tcgdexSetId": "ecard3",
      "number": "6",
      "printedTotal": "144",
      "imageUrl": "https://assets.tcgdex.net/en/ecard/ecard3/6",
      "types": [],
      "rarity": ""
    },
    {
      "id": "ecard3-7",
      "name": "Dewgong",
      "searchName": "Dewgong",
      "collectionId": "ecard3",
      "collectionName": "Skyridge",
      "ligaSetCode": "SK",
      "tcgdexSetId": "ecard3",
      "number": "7",
      "printedTotal": "144",
      "imageUrl": "https://assets.tcgdex.net/en/ecard/ecard3/7",
      "types": [],
      "rarity": ""
    },
    {
      "id": "ecard3-8",
      "name": "Flareon",
      "searchName": "Flareon",
      "collectionId": "ecard3",
      "collectionName": "Skyridge",
      "ligaSetCode": "SK",
      "tcgdexSetId": "ecard3",
      "number": "8",
      "printedTotal": "144",
      "imageUrl": "https://assets.tcgdex.net/en/ecard/ecard3/8",
      "types": [],
      "rarity": ""
    },
    {
      "id": "ecard3-9",
      "name": "Forretress",
      "searchName": "Forretress",
      "collectionId": "ecard3",
      "collectionName": "Skyridge",
      "ligaSetCode": "SK",
      "tcgdexSetId": "ecard3",
      "number": "9",
      "printedTotal": "144",
      "imageUrl": "https://assets.tcgdex.net/en/ecard/ecard3/9",
      "types": [],
      "rarity": ""
    },
    {
      "id": "ecard3-10",
      "name": "Gengar",
      "searchName": "Gengar",
      "collectionId": "ecard3",
      "collectionName": "Skyridge",
      "ligaSetCode": "SK",
      "tcgdexSetId": "ecard3",
      "number": "10",
      "printedTotal": "144",
      "imageUrl": "https://assets.tcgdex.net/en/ecard/ecard3/10",
      "types": [],
      "rarity": ""
    },
    {
      "id": "ecard3-11",
      "name": "Gyarados",
      "searchName": "Gyarados",
      "collectionId": "ecard3",
      "collectionName": "Skyridge",
      "ligaSetCode": "SK",
      "tcgdexSetId": "ecard3",
      "number": "11",
      "printedTotal": "144",
      "imageUrl": "https://assets.tcgdex.net/en/ecard/ecard3/11",
      "types": [],
      "rarity": ""
    },
    {
      "id": "ecard3-12",
      "name": "Houndoom",
      "searchName": "Houndoom",
      "collectionId": "ecard3",
      "collectionName": "Skyridge",
      "ligaSetCode": "SK",
      "tcgdexSetId": "ecard3",
      "number": "12",
      "printedTotal": "144",
      "imageUrl": "https://assets.tcgdex.net/en/ecard/ecard3/12",
      "types": [],
      "rarity": ""
    },
    {
      "id": "ecard3-13",
      "name": "Jolteon",
      "searchName": "Jolteon",
      "collectionId": "ecard3",
      "collectionName": "Skyridge",
      "ligaSetCode": "SK",
      "tcgdexSetId": "ecard3",
      "number": "13",
      "printedTotal": "144",
      "imageUrl": "https://assets.tcgdex.net/en/ecard/ecard3/13",
      "types": [],
      "rarity": ""
    },
    {
      "id": "ecard3-14",
      "name": "Kabutops",
      "searchName": "Kabutops",
      "collectionId": "ecard3",
      "collectionName": "Skyridge",
      "ligaSetCode": "SK",
      "tcgdexSetId": "ecard3",
      "number": "14",
      "printedTotal": "144",
      "imageUrl": "https://assets.tcgdex.net/en/ecard/ecard3/14",
      "types": [],
      "rarity": ""
    },
    {
      "id": "ecard3-15",
      "name": "Ledian",
      "searchName": "Ledian",
      "collectionId": "ecard3",
      "collectionName": "Skyridge",
      "ligaSetCode": "SK",
      "tcgdexSetId": "ecard3",
      "number": "15",
      "printedTotal": "144",
      "imageUrl": "https://assets.tcgdex.net/en/ecard/ecard3/15",
      "types": [],
      "rarity": ""
    },
    {
      "id": "ecard3-16",
      "name": "Machamp",
      "searchName": "Machamp",
      "collectionId": "ecard3",
      "collectionName": "Skyridge",
      "ligaSetCode": "SK",
      "tcgdexSetId": "ecard3",
      "number": "16",
      "printedTotal": "144",
      "imageUrl": "https://assets.tcgdex.net/en/ecard/ecard3/16",
      "types": [],
      "rarity": ""
    },
    {
      "id": "ecard3-17",
      "name": "Magcargo",
      "searchName": "Magcargo",
      "collectionId": "ecard3",
      "collectionName": "Skyridge",
      "ligaSetCode": "SK",
      "tcgdexSetId": "ecard3",
      "number": "17",
      "printedTotal": "144",
      "imageUrl": "https://assets.tcgdex.net/en/ecard/ecard3/17",
      "types": [],
      "rarity": ""
    },
    {
      "id": "ecard3-18",
      "name": "Magcargo",
      "searchName": "Magcargo",
      "collectionId": "ecard3",
      "collectionName": "Skyridge",
      "ligaSetCode": "SK",
      "tcgdexSetId": "ecard3",
      "number": "18",
      "printedTotal": "144",
      "imageUrl": "https://assets.tcgdex.net/en/ecard/ecard3/18",
      "types": [],
      "rarity": ""
    },
    {
      "id": "ecard3-19",
      "name": "Magneton",
      "searchName": "Magneton",
      "collectionId": "ecard3",
      "collectionName": "Skyridge",
      "ligaSetCode": "SK",
      "tcgdexSetId": "ecard3",
      "number": "19",
      "printedTotal": "144",
      "imageUrl": "https://assets.tcgdex.net/en/ecard/ecard3/19",
      "types": [],
      "rarity": ""
    },
    {
      "id": "ecard3-20",
      "name": "Magneton",
      "searchName": "Magneton",
      "collectionId": "ecard3",
      "collectionName": "Skyridge",
      "ligaSetCode": "SK",
      "tcgdexSetId": "ecard3",
      "number": "20",
      "printedTotal": "144",
      "imageUrl": "https://assets.tcgdex.net/en/ecard/ecard3/20",
      "types": [],
      "rarity": ""
    },
    {
      "id": "ecard3-21",
      "name": "Moltres",
      "searchName": "Moltres",
      "collectionId": "ecard3",
      "collectionName": "Skyridge",
      "ligaSetCode": "SK",
      "tcgdexSetId": "ecard3",
      "number": "21",
      "printedTotal": "144",
      "imageUrl": "https://assets.tcgdex.net/en/ecard/ecard3/21",
      "types": [],
      "rarity": ""
    },
    {
      "id": "ecard3-22",
      "name": "Nidoqueen",
      "searchName": "Nidoqueen",
      "collectionId": "ecard3",
      "collectionName": "Skyridge",
      "ligaSetCode": "SK",
      "tcgdexSetId": "ecard3",
      "number": "22",
      "printedTotal": "144",
      "imageUrl": "https://assets.tcgdex.net/en/ecard/ecard3/22",
      "types": [],
      "rarity": ""
    },
    {
      "id": "ecard3-23",
      "name": "Omastar",
      "searchName": "Omastar",
      "collectionId": "ecard3",
      "collectionName": "Skyridge",
      "ligaSetCode": "SK",
      "tcgdexSetId": "ecard3",
      "number": "23",
      "printedTotal": "144",
      "imageUrl": "https://assets.tcgdex.net/en/ecard/ecard3/23",
      "types": [],
      "rarity": ""
    },
    {
      "id": "ecard3-24",
      "name": "Piloswine",
      "searchName": "Piloswine",
      "collectionId": "ecard3",
      "collectionName": "Skyridge",
      "ligaSetCode": "SK",
      "tcgdexSetId": "ecard3",
      "number": "24",
      "printedTotal": "144",
      "imageUrl": "https://assets.tcgdex.net/en/ecard/ecard3/24",
      "types": [],
      "rarity": ""
    },
    {
      "id": "ecard3-25",
      "name": "Politoed",
      "searchName": "Politoed",
      "collectionId": "ecard3",
      "collectionName": "Skyridge",
      "ligaSetCode": "SK",
      "tcgdexSetId": "ecard3",
      "number": "25",
      "printedTotal": "144",
      "imageUrl": "https://assets.tcgdex.net/en/ecard/ecard3/25",
      "types": [],
      "rarity": ""
    },
    {
      "id": "ecard3-26",
      "name": "Poliwrath",
      "searchName": "Poliwrath",
      "collectionId": "ecard3",
      "collectionName": "Skyridge",
      "ligaSetCode": "SK",
      "tcgdexSetId": "ecard3",
      "number": "26",
      "printedTotal": "144",
      "imageUrl": "https://assets.tcgdex.net/en/ecard/ecard3/26",
      "types": [],
      "rarity": ""
    },
    {
      "id": "ecard3-27",
      "name": "Raichu",
      "searchName": "Raichu",
      "collectionId": "ecard3",
      "collectionName": "Skyridge",
      "ligaSetCode": "SK",
      "tcgdexSetId": "ecard3",
      "number": "27",
      "printedTotal": "144",
      "imageUrl": "https://assets.tcgdex.net/en/ecard/ecard3/27",
      "types": [],
      "rarity": ""
    },
    {
      "id": "ecard3-28",
      "name": "Raikou",
      "searchName": "Raikou",
      "collectionId": "ecard3",
      "collectionName": "Skyridge",
      "ligaSetCode": "SK",
      "tcgdexSetId": "ecard3",
      "number": "28",
      "printedTotal": "144",
      "imageUrl": "https://assets.tcgdex.net/en/ecard/ecard3/28",
      "types": [],
      "rarity": ""
    },
    {
      "id": "ecard3-29",
      "name": "Rhydon",
      "searchName": "Rhydon",
      "collectionId": "ecard3",
      "collectionName": "Skyridge",
      "ligaSetCode": "SK",
      "tcgdexSetId": "ecard3",
      "number": "29",
      "printedTotal": "144",
      "imageUrl": "https://assets.tcgdex.net/en/ecard/ecard3/29",
      "types": [],
      "rarity": ""
    },
    {
      "id": "ecard3-30",
      "name": "Starmie",
      "searchName": "Starmie",
      "collectionId": "ecard3",
      "collectionName": "Skyridge",
      "ligaSetCode": "SK",
      "tcgdexSetId": "ecard3",
      "number": "30",
      "printedTotal": "144",
      "imageUrl": "https://assets.tcgdex.net/en/ecard/ecard3/30",
      "types": [],
      "rarity": ""
    },
    {
      "id": "ecard3-31",
      "name": "Steelix",
      "searchName": "Steelix",
      "collectionId": "ecard3",
      "collectionName": "Skyridge",
      "ligaSetCode": "SK",
      "tcgdexSetId": "ecard3",
      "number": "31",
      "printedTotal": "144",
      "imageUrl": "https://assets.tcgdex.net/en/ecard/ecard3/31",
      "types": [],
      "rarity": ""
    },
    {
      "id": "ecard3-32",
      "name": "Umbreon",
      "searchName": "Umbreon",
      "collectionId": "ecard3",
      "collectionName": "Skyridge",
      "ligaSetCode": "SK",
      "tcgdexSetId": "ecard3",
      "number": "32",
      "printedTotal": "144",
      "imageUrl": "https://assets.tcgdex.net/en/ecard/ecard3/32",
      "types": [],
      "rarity": ""
    },
    {
      "id": "ecard3-33",
      "name": "Vaporeon",
      "searchName": "Vaporeon",
      "collectionId": "ecard3",
      "collectionName": "Skyridge",
      "ligaSetCode": "SK",
      "tcgdexSetId": "ecard3",
      "number": "33",
      "printedTotal": "144",
      "imageUrl": "https://assets.tcgdex.net/en/ecard/ecard3/33",
      "types": [],
      "rarity": ""
    },
    {
      "id": "ecard3-34",
      "name": "Wigglytuff",
      "searchName": "Wigglytuff",
      "collectionId": "ecard3",
      "collectionName": "Skyridge",
      "ligaSetCode": "SK",
      "tcgdexSetId": "ecard3",
      "number": "34",
      "printedTotal": "144",
      "imageUrl": "https://assets.tcgdex.net/en/ecard/ecard3/34",
      "types": [],
      "rarity": ""
    },
    {
      "id": "ecard3-35",
      "name": "Xatu",
      "searchName": "Xatu",
      "collectionId": "ecard3",
      "collectionName": "Skyridge",
      "ligaSetCode": "SK",
      "tcgdexSetId": "ecard3",
      "number": "35",
      "printedTotal": "144",
      "imageUrl": "https://assets.tcgdex.net/en/ecard/ecard3/35",
      "types": [],
      "rarity": ""
    },
    {
      "id": "ecard3-36",
      "name": "Electrode",
      "searchName": "Electrode",
      "collectionId": "ecard3",
      "collectionName": "Skyridge",
      "ligaSetCode": "SK",
      "tcgdexSetId": "ecard3",
      "number": "36",
      "printedTotal": "144",
      "imageUrl": "https://assets.tcgdex.net/en/ecard/ecard3/36",
      "types": [],
      "rarity": ""
    },
    {
      "id": "ecard3-37",
      "name": "Kabuto",
      "searchName": "Kabuto",
      "collectionId": "ecard3",
      "collectionName": "Skyridge",
      "ligaSetCode": "SK",
      "tcgdexSetId": "ecard3",
      "number": "37",
      "printedTotal": "144",
      "imageUrl": "https://assets.tcgdex.net/en/ecard/ecard3/37",
      "types": [],
      "rarity": ""
    },
    {
      "id": "ecard3-38",
      "name": "Machoke",
      "searchName": "Machoke",
      "collectionId": "ecard3",
      "collectionName": "Skyridge",
      "ligaSetCode": "SK",
      "tcgdexSetId": "ecard3",
      "number": "38",
      "printedTotal": "144",
      "imageUrl": "https://assets.tcgdex.net/en/ecard/ecard3/38",
      "types": [],
      "rarity": ""
    },
    {
      "id": "ecard3-39",
      "name": "Misdreavus",
      "searchName": "Misdreavus",
      "collectionId": "ecard3",
      "collectionName": "Skyridge",
      "ligaSetCode": "SK",
      "tcgdexSetId": "ecard3",
      "number": "39",
      "printedTotal": "144",
      "imageUrl": "https://assets.tcgdex.net/en/ecard/ecard3/39",
      "types": [],
      "rarity": ""
    },
    {
      "id": "ecard3-40",
      "name": "Noctowl",
      "searchName": "Noctowl",
      "collectionId": "ecard3",
      "collectionName": "Skyridge",
      "ligaSetCode": "SK",
      "tcgdexSetId": "ecard3",
      "number": "40",
      "printedTotal": "144",
      "imageUrl": "https://assets.tcgdex.net/en/ecard/ecard3/40",
      "types": [],
      "rarity": ""
    },
    {
      "id": "ecard3-41",
      "name": "Omanyte",
      "searchName": "Omanyte",
      "collectionId": "ecard3",
      "collectionName": "Skyridge",
      "ligaSetCode": "SK",
      "tcgdexSetId": "ecard3",
      "number": "41",
      "printedTotal": "144",
      "imageUrl": "https://assets.tcgdex.net/en/ecard/ecard3/41",
      "types": [],
      "rarity": ""
    },
    {
      "id": "ecard3-42",
      "name": "Persian",
      "searchName": "Persian",
      "collectionId": "ecard3",
      "collectionName": "Skyridge",
      "ligaSetCode": "SK",
      "tcgdexSetId": "ecard3",
      "number": "42",
      "printedTotal": "144",
      "imageUrl": "https://assets.tcgdex.net/en/ecard/ecard3/42",
      "types": [],
      "rarity": ""
    },
    {
      "id": "ecard3-43",
      "name": "Piloswine",
      "searchName": "Piloswine",
      "collectionId": "ecard3",
      "collectionName": "Skyridge",
      "ligaSetCode": "SK",
      "tcgdexSetId": "ecard3",
      "number": "43",
      "printedTotal": "144",
      "imageUrl": "https://assets.tcgdex.net/en/ecard/ecard3/43",
      "types": [],
      "rarity": ""
    },
    {
      "id": "ecard3-44",
      "name": "Starmie",
      "searchName": "Starmie",
      "collectionId": "ecard3",
      "collectionName": "Skyridge",
      "ligaSetCode": "SK",
      "tcgdexSetId": "ecard3",
      "number": "44",
      "printedTotal": "144",
      "imageUrl": "https://assets.tcgdex.net/en/ecard/ecard3/44",
      "types": [],
      "rarity": ""
    },
    {
      "id": "ecard3-45",
      "name": "Wobbuffet",
      "searchName": "Wobbuffet",
      "collectionId": "ecard3",
      "collectionName": "Skyridge",
      "ligaSetCode": "SK",
      "tcgdexSetId": "ecard3",
      "number": "45",
      "printedTotal": "144",
      "imageUrl": "https://assets.tcgdex.net/en/ecard/ecard3/45",
      "types": [],
      "rarity": ""
    },
    {
      "id": "ecard3-46",
      "name": "Abra",
      "searchName": "Abra",
      "collectionId": "ecard3",
      "collectionName": "Skyridge",
      "ligaSetCode": "SK",
      "tcgdexSetId": "ecard3",
      "number": "46",
      "printedTotal": "144",
      "imageUrl": "https://assets.tcgdex.net/en/ecard/ecard3/46",
      "types": [],
      "rarity": ""
    },
    {
      "id": "ecard3-47",
      "name": "Buried Fossil",
      "searchName": "Buried Fossil",
      "collectionId": "ecard3",
      "collectionName": "Skyridge",
      "ligaSetCode": "SK",
      "tcgdexSetId": "ecard3",
      "number": "47",
      "printedTotal": "144",
      "imageUrl": "https://assets.tcgdex.net/en/ecard/ecard3/47",
      "types": [],
      "rarity": ""
    },
    {
      "id": "ecard3-48",
      "name": "Cleffa",
      "searchName": "Cleffa",
      "collectionId": "ecard3",
      "collectionName": "Skyridge",
      "ligaSetCode": "SK",
      "tcgdexSetId": "ecard3",
      "number": "48",
      "printedTotal": "144",
      "imageUrl": "https://assets.tcgdex.net/en/ecard/ecard3/48",
      "types": [],
      "rarity": ""
    },
    {
      "id": "ecard3-49",
      "name": "Delibird",
      "searchName": "Delibird",
      "collectionId": "ecard3",
      "collectionName": "Skyridge",
      "ligaSetCode": "SK",
      "tcgdexSetId": "ecard3",
      "number": "49",
      "printedTotal": "144",
      "imageUrl": "https://assets.tcgdex.net/en/ecard/ecard3/49",
      "types": [],
      "rarity": ""
    },
    {
      "id": "ecard3-50",
      "name": "Diglett",
      "searchName": "Diglett",
      "collectionId": "ecard3",
      "collectionName": "Skyridge",
      "ligaSetCode": "SK",
      "tcgdexSetId": "ecard3",
      "number": "50",
      "printedTotal": "144",
      "imageUrl": "https://assets.tcgdex.net/en/ecard/ecard3/50",
      "types": [],
      "rarity": ""
    },
    {
      "id": "ecard3-51",
      "name": "Ditto",
      "searchName": "Ditto",
      "collectionId": "ecard3",
      "collectionName": "Skyridge",
      "ligaSetCode": "SK",
      "tcgdexSetId": "ecard3",
      "number": "51",
      "printedTotal": "144",
      "imageUrl": "https://assets.tcgdex.net/en/ecard/ecard3/51",
      "types": [],
      "rarity": ""
    },
    {
      "id": "ecard3-52",
      "name": "Dugtrio",
      "searchName": "Dugtrio",
      "collectionId": "ecard3",
      "collectionName": "Skyridge",
      "ligaSetCode": "SK",
      "tcgdexSetId": "ecard3",
      "number": "52",
      "printedTotal": "144",
      "imageUrl": "https://assets.tcgdex.net/en/ecard/ecard3/52",
      "types": [],
      "rarity": ""
    },
    {
      "id": "ecard3-53",
      "name": "Dunsparce",
      "searchName": "Dunsparce",
      "collectionId": "ecard3",
      "collectionName": "Skyridge",
      "ligaSetCode": "SK",
      "tcgdexSetId": "ecard3",
      "number": "53",
      "printedTotal": "144",
      "imageUrl": "https://assets.tcgdex.net/en/ecard/ecard3/53",
      "types": [],
      "rarity": ""
    },
    {
      "id": "ecard3-54",
      "name": "Eevee",
      "searchName": "Eevee",
      "collectionId": "ecard3",
      "collectionName": "Skyridge",
      "ligaSetCode": "SK",
      "tcgdexSetId": "ecard3",
      "number": "54",
      "printedTotal": "144",
      "imageUrl": "https://assets.tcgdex.net/en/ecard/ecard3/54",
      "types": [],
      "rarity": ""
    },
    {
      "id": "ecard3-55",
      "name": "Farfetch'd",
      "searchName": "Farfetch'd",
      "collectionId": "ecard3",
      "collectionName": "Skyridge",
      "ligaSetCode": "SK",
      "tcgdexSetId": "ecard3",
      "number": "55",
      "printedTotal": "144",
      "imageUrl": "https://assets.tcgdex.net/en/ecard/ecard3/55",
      "types": [],
      "rarity": ""
    },
    {
      "id": "ecard3-56",
      "name": "Forretress",
      "searchName": "Forretress",
      "collectionId": "ecard3",
      "collectionName": "Skyridge",
      "ligaSetCode": "SK",
      "tcgdexSetId": "ecard3",
      "number": "56",
      "printedTotal": "144",
      "imageUrl": "https://assets.tcgdex.net/en/ecard/ecard3/56",
      "types": [],
      "rarity": ""
    },
    {
      "id": "ecard3-57",
      "name": "Gastly",
      "searchName": "Gastly",
      "collectionId": "ecard3",
      "collectionName": "Skyridge",
      "ligaSetCode": "SK",
      "tcgdexSetId": "ecard3",
      "number": "57",
      "printedTotal": "144",
      "imageUrl": "https://assets.tcgdex.net/en/ecard/ecard3/57",
      "types": [],
      "rarity": ""
    },
    {
      "id": "ecard3-58",
      "name": "Girafarig",
      "searchName": "Girafarig",
      "collectionId": "ecard3",
      "collectionName": "Skyridge",
      "ligaSetCode": "SK",
      "tcgdexSetId": "ecard3",
      "number": "58",
      "printedTotal": "144",
      "imageUrl": "https://assets.tcgdex.net/en/ecard/ecard3/58",
      "types": [],
      "rarity": ""
    },
    {
      "id": "ecard3-59",
      "name": "Gligar",
      "searchName": "Gligar",
      "collectionId": "ecard3",
      "collectionName": "Skyridge",
      "ligaSetCode": "SK",
      "tcgdexSetId": "ecard3",
      "number": "59",
      "printedTotal": "144",
      "imageUrl": "https://assets.tcgdex.net/en/ecard/ecard3/59",
      "types": [],
      "rarity": ""
    },
    {
      "id": "ecard3-60",
      "name": "Golbat",
      "searchName": "Golbat",
      "collectionId": "ecard3",
      "collectionName": "Skyridge",
      "ligaSetCode": "SK",
      "tcgdexSetId": "ecard3",
      "number": "60",
      "printedTotal": "144",
      "imageUrl": "https://assets.tcgdex.net/en/ecard/ecard3/60",
      "types": [],
      "rarity": ""
    },
    {
      "id": "ecard3-61",
      "name": "Granbull",
      "searchName": "Granbull",
      "collectionId": "ecard3",
      "collectionName": "Skyridge",
      "ligaSetCode": "SK",
      "tcgdexSetId": "ecard3",
      "number": "61",
      "printedTotal": "144",
      "imageUrl": "https://assets.tcgdex.net/en/ecard/ecard3/61",
      "types": [],
      "rarity": ""
    },
    {
      "id": "ecard3-62",
      "name": "Growlithe",
      "searchName": "Growlithe",
      "collectionId": "ecard3",
      "collectionName": "Skyridge",
      "ligaSetCode": "SK",
      "tcgdexSetId": "ecard3",
      "number": "62",
      "printedTotal": "144",
      "imageUrl": "https://assets.tcgdex.net/en/ecard/ecard3/62",
      "types": [],
      "rarity": ""
    },
    {
      "id": "ecard3-63",
      "name": "Haunter",
      "searchName": "Haunter",
      "collectionId": "ecard3",
      "collectionName": "Skyridge",
      "ligaSetCode": "SK",
      "tcgdexSetId": "ecard3",
      "number": "63",
      "printedTotal": "144",
      "imageUrl": "https://assets.tcgdex.net/en/ecard/ecard3/63",
      "types": [],
      "rarity": ""
    },
    {
      "id": "ecard3-64",
      "name": "Heracross",
      "searchName": "Heracross",
      "collectionId": "ecard3",
      "collectionName": "Skyridge",
      "ligaSetCode": "SK",
      "tcgdexSetId": "ecard3",
      "number": "64",
      "printedTotal": "144",
      "imageUrl": "https://assets.tcgdex.net/en/ecard/ecard3/64",
      "types": [],
      "rarity": ""
    },
    {
      "id": "ecard3-65",
      "name": "Hoothoot",
      "searchName": "Hoothoot",
      "collectionId": "ecard3",
      "collectionName": "Skyridge",
      "ligaSetCode": "SK",
      "tcgdexSetId": "ecard3",
      "number": "65",
      "printedTotal": "144",
      "imageUrl": "https://assets.tcgdex.net/en/ecard/ecard3/65",
      "types": [],
      "rarity": ""
    },
    {
      "id": "ecard3-66",
      "name": "Houndour",
      "searchName": "Houndour",
      "collectionId": "ecard3",
      "collectionName": "Skyridge",
      "ligaSetCode": "SK",
      "tcgdexSetId": "ecard3",
      "number": "66",
      "printedTotal": "144",
      "imageUrl": "https://assets.tcgdex.net/en/ecard/ecard3/66",
      "types": [],
      "rarity": ""
    },
    {
      "id": "ecard3-67",
      "name": "Igglybuff",
      "searchName": "Igglybuff",
      "collectionId": "ecard3",
      "collectionName": "Skyridge",
      "ligaSetCode": "SK",
      "tcgdexSetId": "ecard3",
      "number": "67",
      "printedTotal": "144",
      "imageUrl": "https://assets.tcgdex.net/en/ecard/ecard3/67",
      "types": [],
      "rarity": ""
    },
    {
      "id": "ecard3-68",
      "name": "Jigglypuff",
      "searchName": "Jigglypuff",
      "collectionId": "ecard3",
      "collectionName": "Skyridge",
      "ligaSetCode": "SK",
      "tcgdexSetId": "ecard3",
      "number": "68",
      "printedTotal": "144",
      "imageUrl": "https://assets.tcgdex.net/en/ecard/ecard3/68",
      "types": [],
      "rarity": ""
    },
    {
      "id": "ecard3-69",
      "name": "Kadabra",
      "searchName": "Kadabra",
      "collectionId": "ecard3",
      "collectionName": "Skyridge",
      "ligaSetCode": "SK",
      "tcgdexSetId": "ecard3",
      "number": "69",
      "printedTotal": "144",
      "imageUrl": "https://assets.tcgdex.net/en/ecard/ecard3/69",
      "types": [],
      "rarity": ""
    },
    {
      "id": "ecard3-70",
      "name": "Kakuna",
      "searchName": "Kakuna",
      "collectionId": "ecard3",
      "collectionName": "Skyridge",
      "ligaSetCode": "SK",
      "tcgdexSetId": "ecard3",
      "number": "70",
      "printedTotal": "144",
      "imageUrl": "https://assets.tcgdex.net/en/ecard/ecard3/70",
      "types": [],
      "rarity": ""
    },
    {
      "id": "ecard3-71",
      "name": "Lapras",
      "searchName": "Lapras",
      "collectionId": "ecard3",
      "collectionName": "Skyridge",
      "ligaSetCode": "SK",
      "tcgdexSetId": "ecard3",
      "number": "71",
      "printedTotal": "144",
      "imageUrl": "https://assets.tcgdex.net/en/ecard/ecard3/71",
      "types": [],
      "rarity": ""
    },
    {
      "id": "ecard3-72",
      "name": "Ledyba",
      "searchName": "Ledyba",
      "collectionId": "ecard3",
      "collectionName": "Skyridge",
      "ligaSetCode": "SK",
      "tcgdexSetId": "ecard3",
      "number": "72",
      "printedTotal": "144",
      "imageUrl": "https://assets.tcgdex.net/en/ecard/ecard3/72",
      "types": [],
      "rarity": ""
    },
    {
      "id": "ecard3-73",
      "name": "Ledyba",
      "searchName": "Ledyba",
      "collectionId": "ecard3",
      "collectionName": "Skyridge",
      "ligaSetCode": "SK",
      "tcgdexSetId": "ecard3",
      "number": "73",
      "printedTotal": "144",
      "imageUrl": "https://assets.tcgdex.net/en/ecard/ecard3/73",
      "types": [],
      "rarity": ""
    },
    {
      "id": "ecard3-74",
      "name": "Machop",
      "searchName": "Machop",
      "collectionId": "ecard3",
      "collectionName": "Skyridge",
      "ligaSetCode": "SK",
      "tcgdexSetId": "ecard3",
      "number": "74",
      "printedTotal": "144",
      "imageUrl": "https://assets.tcgdex.net/en/ecard/ecard3/74",
      "types": [],
      "rarity": ""
    },
    {
      "id": "ecard3-75",
      "name": "Magikarp",
      "searchName": "Magikarp",
      "collectionId": "ecard3",
      "collectionName": "Skyridge",
      "ligaSetCode": "SK",
      "tcgdexSetId": "ecard3",
      "number": "75",
      "printedTotal": "144",
      "imageUrl": "https://assets.tcgdex.net/en/ecard/ecard3/75",
      "types": [],
      "rarity": ""
    },
    {
      "id": "ecard3-76",
      "name": "Magnemite",
      "searchName": "Magnemite",
      "collectionId": "ecard3",
      "collectionName": "Skyridge",
      "ligaSetCode": "SK",
      "tcgdexSetId": "ecard3",
      "number": "76",
      "printedTotal": "144",
      "imageUrl": "https://assets.tcgdex.net/en/ecard/ecard3/76",
      "types": [],
      "rarity": ""
    },
    {
      "id": "ecard3-77",
      "name": "Mantine",
      "searchName": "Mantine",
      "collectionId": "ecard3",
      "collectionName": "Skyridge",
      "ligaSetCode": "SK",
      "tcgdexSetId": "ecard3",
      "number": "77",
      "printedTotal": "144",
      "imageUrl": "https://assets.tcgdex.net/en/ecard/ecard3/77",
      "types": [],
      "rarity": ""
    },
    {
      "id": "ecard3-78",
      "name": "Meowth",
      "searchName": "Meowth",
      "collectionId": "ecard3",
      "collectionName": "Skyridge",
      "ligaSetCode": "SK",
      "tcgdexSetId": "ecard3",
      "number": "78",
      "printedTotal": "144",
      "imageUrl": "https://assets.tcgdex.net/en/ecard/ecard3/78",
      "types": [],
      "rarity": ""
    },
    {
      "id": "ecard3-79",
      "name": "Murkrow",
      "searchName": "Murkrow",
      "collectionId": "ecard3",
      "collectionName": "Skyridge",
      "ligaSetCode": "SK",
      "tcgdexSetId": "ecard3",
      "number": "79",
      "printedTotal": "144",
      "imageUrl": "https://assets.tcgdex.net/en/ecard/ecard3/79",
      "types": [],
      "rarity": ""
    },
    {
      "id": "ecard3-80",
      "name": "Natu",
      "searchName": "Natu",
      "collectionId": "ecard3",
      "collectionName": "Skyridge",
      "ligaSetCode": "SK",
      "tcgdexSetId": "ecard3",
      "number": "80",
      "printedTotal": "144",
      "imageUrl": "https://assets.tcgdex.net/en/ecard/ecard3/80",
      "types": [],
      "rarity": ""
    },
    {
      "id": "ecard3-81",
      "name": "Nidoran♀",
      "searchName": "Nidoran♀",
      "collectionId": "ecard3",
      "collectionName": "Skyridge",
      "ligaSetCode": "SK",
      "tcgdexSetId": "ecard3",
      "number": "81",
      "printedTotal": "144",
      "imageUrl": "https://assets.tcgdex.net/en/ecard/ecard3/81",
      "types": [],
      "rarity": ""
    },
    {
      "id": "ecard3-82",
      "name": "Nidoran♀",
      "searchName": "Nidoran♀",
      "collectionId": "ecard3",
      "collectionName": "Skyridge",
      "ligaSetCode": "SK",
      "tcgdexSetId": "ecard3",
      "number": "82",
      "printedTotal": "144",
      "imageUrl": "https://assets.tcgdex.net/en/ecard/ecard3/82",
      "types": [],
      "rarity": ""
    },
    {
      "id": "ecard3-83",
      "name": "Nidorina",
      "searchName": "Nidorina",
      "collectionId": "ecard3",
      "collectionName": "Skyridge",
      "ligaSetCode": "SK",
      "tcgdexSetId": "ecard3",
      "number": "83",
      "printedTotal": "144",
      "imageUrl": "https://assets.tcgdex.net/en/ecard/ecard3/83",
      "types": [],
      "rarity": ""
    },
    {
      "id": "ecard3-84",
      "name": "Pikachu",
      "searchName": "Pikachu",
      "collectionId": "ecard3",
      "collectionName": "Skyridge",
      "ligaSetCode": "SK",
      "tcgdexSetId": "ecard3",
      "number": "84",
      "printedTotal": "144",
      "imageUrl": "https://assets.tcgdex.net/en/ecard/ecard3/84",
      "types": [],
      "rarity": ""
    },
    {
      "id": "ecard3-85",
      "name": "Pineco",
      "searchName": "Pineco",
      "collectionId": "ecard3",
      "collectionName": "Skyridge",
      "ligaSetCode": "SK",
      "tcgdexSetId": "ecard3",
      "number": "85",
      "printedTotal": "144",
      "imageUrl": "https://assets.tcgdex.net/en/ecard/ecard3/85",
      "types": [],
      "rarity": ""
    },
    {
      "id": "ecard3-86",
      "name": "Pineco",
      "searchName": "Pineco",
      "collectionId": "ecard3",
      "collectionName": "Skyridge",
      "ligaSetCode": "SK",
      "tcgdexSetId": "ecard3",
      "number": "86",
      "printedTotal": "144",
      "imageUrl": "https://assets.tcgdex.net/en/ecard/ecard3/86",
      "types": [],
      "rarity": ""
    },
    {
      "id": "ecard3-87",
      "name": "Poliwag",
      "searchName": "Poliwag",
      "collectionId": "ecard3",
      "collectionName": "Skyridge",
      "ligaSetCode": "SK",
      "tcgdexSetId": "ecard3",
      "number": "87",
      "printedTotal": "144",
      "imageUrl": "https://assets.tcgdex.net/en/ecard/ecard3/87",
      "types": [],
      "rarity": ""
    },
    {
      "id": "ecard3-88",
      "name": "Poliwhirl",
      "searchName": "Poliwhirl",
      "collectionId": "ecard3",
      "collectionName": "Skyridge",
      "ligaSetCode": "SK",
      "tcgdexSetId": "ecard3",
      "number": "88",
      "printedTotal": "144",
      "imageUrl": "https://assets.tcgdex.net/en/ecard/ecard3/88",
      "types": [],
      "rarity": ""
    },
    {
      "id": "ecard3-89",
      "name": "Raticate",
      "searchName": "Raticate",
      "collectionId": "ecard3",
      "collectionName": "Skyridge",
      "ligaSetCode": "SK",
      "tcgdexSetId": "ecard3",
      "number": "89",
      "printedTotal": "144",
      "imageUrl": "https://assets.tcgdex.net/en/ecard/ecard3/89",
      "types": [],
      "rarity": ""
    },
    {
      "id": "ecard3-90",
      "name": "Rattata",
      "searchName": "Rattata",
      "collectionId": "ecard3",
      "collectionName": "Skyridge",
      "ligaSetCode": "SK",
      "tcgdexSetId": "ecard3",
      "number": "90",
      "printedTotal": "144",
      "imageUrl": "https://assets.tcgdex.net/en/ecard/ecard3/90",
      "types": [],
      "rarity": ""
    },
    {
      "id": "ecard3-91",
      "name": "Rhyhorn",
      "searchName": "Rhyhorn",
      "collectionId": "ecard3",
      "collectionName": "Skyridge",
      "ligaSetCode": "SK",
      "tcgdexSetId": "ecard3",
      "number": "91",
      "printedTotal": "144",
      "imageUrl": "https://assets.tcgdex.net/en/ecard/ecard3/91",
      "types": [],
      "rarity": ""
    },
    {
      "id": "ecard3-92",
      "name": "Sandshrew",
      "searchName": "Sandshrew",
      "collectionId": "ecard3",
      "collectionName": "Skyridge",
      "ligaSetCode": "SK",
      "tcgdexSetId": "ecard3",
      "number": "92",
      "printedTotal": "144",
      "imageUrl": "https://assets.tcgdex.net/en/ecard/ecard3/92",
      "types": [],
      "rarity": ""
    },
    {
      "id": "ecard3-93",
      "name": "Sandslash",
      "searchName": "Sandslash",
      "collectionId": "ecard3",
      "collectionName": "Skyridge",
      "ligaSetCode": "SK",
      "tcgdexSetId": "ecard3",
      "number": "93",
      "printedTotal": "144",
      "imageUrl": "https://assets.tcgdex.net/en/ecard/ecard3/93",
      "types": [],
      "rarity": ""
    },
    {
      "id": "ecard3-94",
      "name": "Seel",
      "searchName": "Seel",
      "collectionId": "ecard3",
      "collectionName": "Skyridge",
      "ligaSetCode": "SK",
      "tcgdexSetId": "ecard3",
      "number": "94",
      "printedTotal": "144",
      "imageUrl": "https://assets.tcgdex.net/en/ecard/ecard3/94",
      "types": [],
      "rarity": ""
    },
    {
      "id": "ecard3-95",
      "name": "Seel",
      "searchName": "Seel",
      "collectionId": "ecard3",
      "collectionName": "Skyridge",
      "ligaSetCode": "SK",
      "tcgdexSetId": "ecard3",
      "number": "95",
      "printedTotal": "144",
      "imageUrl": "https://assets.tcgdex.net/en/ecard/ecard3/95",
      "types": [],
      "rarity": ""
    },
    {
      "id": "ecard3-96",
      "name": "Shuckle",
      "searchName": "Shuckle",
      "collectionId": "ecard3",
      "collectionName": "Skyridge",
      "ligaSetCode": "SK",
      "tcgdexSetId": "ecard3",
      "number": "96",
      "printedTotal": "144",
      "imageUrl": "https://assets.tcgdex.net/en/ecard/ecard3/96",
      "types": [],
      "rarity": ""
    },
    {
      "id": "ecard3-97",
      "name": "Skarmory",
      "searchName": "Skarmory",
      "collectionId": "ecard3",
      "collectionName": "Skyridge",
      "ligaSetCode": "SK",
      "tcgdexSetId": "ecard3",
      "number": "97",
      "printedTotal": "144",
      "imageUrl": "https://assets.tcgdex.net/en/ecard/ecard3/97",
      "types": [],
      "rarity": ""
    },
    {
      "id": "ecard3-98",
      "name": "Slugma",
      "searchName": "Slugma",
      "collectionId": "ecard3",
      "collectionName": "Skyridge",
      "ligaSetCode": "SK",
      "tcgdexSetId": "ecard3",
      "number": "98",
      "printedTotal": "144",
      "imageUrl": "https://assets.tcgdex.net/en/ecard/ecard3/98",
      "types": [],
      "rarity": ""
    },
    {
      "id": "ecard3-99",
      "name": "Slugma",
      "searchName": "Slugma",
      "collectionId": "ecard3",
      "collectionName": "Skyridge",
      "ligaSetCode": "SK",
      "tcgdexSetId": "ecard3",
      "number": "99",
      "printedTotal": "144",
      "imageUrl": "https://assets.tcgdex.net/en/ecard/ecard3/99",
      "types": [],
      "rarity": ""
    },
    {
      "id": "ecard3-100",
      "name": "Snorlax",
      "searchName": "Snorlax",
      "collectionId": "ecard3",
      "collectionName": "Skyridge",
      "ligaSetCode": "SK",
      "tcgdexSetId": "ecard3",
      "number": "100",
      "printedTotal": "144",
      "imageUrl": "https://assets.tcgdex.net/en/ecard/ecard3/100",
      "types": [],
      "rarity": ""
    },
    {
      "id": "ecard3-101",
      "name": "Snubbull",
      "searchName": "Snubbull",
      "collectionId": "ecard3",
      "collectionName": "Skyridge",
      "ligaSetCode": "SK",
      "tcgdexSetId": "ecard3",
      "number": "101",
      "printedTotal": "144",
      "imageUrl": "https://assets.tcgdex.net/en/ecard/ecard3/101",
      "types": [],
      "rarity": ""
    },
    {
      "id": "ecard3-102",
      "name": "Stantler",
      "searchName": "Stantler",
      "collectionId": "ecard3",
      "collectionName": "Skyridge",
      "ligaSetCode": "SK",
      "tcgdexSetId": "ecard3",
      "number": "102",
      "printedTotal": "144",
      "imageUrl": "https://assets.tcgdex.net/en/ecard/ecard3/102",
      "types": [],
      "rarity": ""
    },
    {
      "id": "ecard3-103",
      "name": "Staryu",
      "searchName": "Staryu",
      "collectionId": "ecard3",
      "collectionName": "Skyridge",
      "ligaSetCode": "SK",
      "tcgdexSetId": "ecard3",
      "number": "103",
      "printedTotal": "144",
      "imageUrl": "https://assets.tcgdex.net/en/ecard/ecard3/103",
      "types": [],
      "rarity": ""
    },
    {
      "id": "ecard3-104",
      "name": "Staryu",
      "searchName": "Staryu",
      "collectionId": "ecard3",
      "collectionName": "Skyridge",
      "ligaSetCode": "SK",
      "tcgdexSetId": "ecard3",
      "number": "104",
      "printedTotal": "144",
      "imageUrl": "https://assets.tcgdex.net/en/ecard/ecard3/104",
      "types": [],
      "rarity": ""
    },
    {
      "id": "ecard3-105",
      "name": "Sunflora",
      "searchName": "Sunflora",
      "collectionId": "ecard3",
      "collectionName": "Skyridge",
      "ligaSetCode": "SK",
      "tcgdexSetId": "ecard3",
      "number": "105",
      "printedTotal": "144",
      "imageUrl": "https://assets.tcgdex.net/en/ecard/ecard3/105",
      "types": [],
      "rarity": ""
    },
    {
      "id": "ecard3-106",
      "name": "Sunkern",
      "searchName": "Sunkern",
      "collectionId": "ecard3",
      "collectionName": "Skyridge",
      "ligaSetCode": "SK",
      "tcgdexSetId": "ecard3",
      "number": "106",
      "printedTotal": "144",
      "imageUrl": "https://assets.tcgdex.net/en/ecard/ecard3/106",
      "types": [],
      "rarity": ""
    },
    {
      "id": "ecard3-107",
      "name": "Swinub",
      "searchName": "Swinub",
      "collectionId": "ecard3",
      "collectionName": "Skyridge",
      "ligaSetCode": "SK",
      "tcgdexSetId": "ecard3",
      "number": "107",
      "printedTotal": "144",
      "imageUrl": "https://assets.tcgdex.net/en/ecard/ecard3/107",
      "types": [],
      "rarity": ""
    },
    {
      "id": "ecard3-108",
      "name": "Swinub",
      "searchName": "Swinub",
      "collectionId": "ecard3",
      "collectionName": "Skyridge",
      "ligaSetCode": "SK",
      "tcgdexSetId": "ecard3",
      "number": "108",
      "printedTotal": "144",
      "imageUrl": "https://assets.tcgdex.net/en/ecard/ecard3/108",
      "types": [],
      "rarity": ""
    },
    {
      "id": "ecard3-109",
      "name": "Teddiursa",
      "searchName": "Teddiursa",
      "collectionId": "ecard3",
      "collectionName": "Skyridge",
      "ligaSetCode": "SK",
      "tcgdexSetId": "ecard3",
      "number": "109",
      "printedTotal": "144",
      "imageUrl": "https://assets.tcgdex.net/en/ecard/ecard3/109",
      "types": [],
      "rarity": ""
    },
    {
      "id": "ecard3-110",
      "name": "Ursaring",
      "searchName": "Ursaring",
      "collectionId": "ecard3",
      "collectionName": "Skyridge",
      "ligaSetCode": "SK",
      "tcgdexSetId": "ecard3",
      "number": "110",
      "printedTotal": "144",
      "imageUrl": "https://assets.tcgdex.net/en/ecard/ecard3/110",
      "types": [],
      "rarity": ""
    },
    {
      "id": "ecard3-111",
      "name": "Venomoth",
      "searchName": "Venomoth",
      "collectionId": "ecard3",
      "collectionName": "Skyridge",
      "ligaSetCode": "SK",
      "tcgdexSetId": "ecard3",
      "number": "111",
      "printedTotal": "144",
      "imageUrl": "https://assets.tcgdex.net/en/ecard/ecard3/111",
      "types": [],
      "rarity": ""
    },
    {
      "id": "ecard3-112",
      "name": "Venonat",
      "searchName": "Venonat",
      "collectionId": "ecard3",
      "collectionName": "Skyridge",
      "ligaSetCode": "SK",
      "tcgdexSetId": "ecard3",
      "number": "112",
      "printedTotal": "144",
      "imageUrl": "https://assets.tcgdex.net/en/ecard/ecard3/112",
      "types": [],
      "rarity": ""
    },
    {
      "id": "ecard3-113",
      "name": "Voltorb",
      "searchName": "Voltorb",
      "collectionId": "ecard3",
      "collectionName": "Skyridge",
      "ligaSetCode": "SK",
      "tcgdexSetId": "ecard3",
      "number": "113",
      "printedTotal": "144",
      "imageUrl": "https://assets.tcgdex.net/en/ecard/ecard3/113",
      "types": [],
      "rarity": ""
    },
    {
      "id": "ecard3-114",
      "name": "Weedle",
      "searchName": "Weedle",
      "collectionId": "ecard3",
      "collectionName": "Skyridge",
      "ligaSetCode": "SK",
      "tcgdexSetId": "ecard3",
      "number": "114",
      "printedTotal": "144",
      "imageUrl": "https://assets.tcgdex.net/en/ecard/ecard3/114",
      "types": [],
      "rarity": ""
    },
    {
      "id": "ecard3-115",
      "name": "Weedle",
      "searchName": "Weedle",
      "collectionId": "ecard3",
      "collectionName": "Skyridge",
      "ligaSetCode": "SK",
      "tcgdexSetId": "ecard3",
      "number": "115",
      "printedTotal": "144",
      "imageUrl": "https://assets.tcgdex.net/en/ecard/ecard3/115",
      "types": [],
      "rarity": ""
    },
    {
      "id": "ecard3-116",
      "name": "Yanma",
      "searchName": "Yanma",
      "collectionId": "ecard3",
      "collectionName": "Skyridge",
      "ligaSetCode": "SK",
      "tcgdexSetId": "ecard3",
      "number": "116",
      "printedTotal": "144",
      "imageUrl": "https://assets.tcgdex.net/en/ecard/ecard3/116",
      "types": [],
      "rarity": ""
    },
    {
      "id": "ecard3-117",
      "name": "Zubat",
      "searchName": "Zubat",
      "collectionId": "ecard3",
      "collectionName": "Skyridge",
      "ligaSetCode": "SK",
      "tcgdexSetId": "ecard3",
      "number": "117",
      "printedTotal": "144",
      "imageUrl": "https://assets.tcgdex.net/en/ecard/ecard3/117",
      "types": [],
      "rarity": ""
    },
    {
      "id": "ecard3-118",
      "name": "Zubat",
      "searchName": "Zubat",
      "collectionId": "ecard3",
      "collectionName": "Skyridge",
      "ligaSetCode": "SK",
      "tcgdexSetId": "ecard3",
      "number": "118",
      "printedTotal": "144",
      "imageUrl": "https://assets.tcgdex.net/en/ecard/ecard3/118",
      "types": [],
      "rarity": ""
    },
    {
      "id": "ecard3-119",
      "name": "Ancient Ruins",
      "searchName": "Ancient Ruins",
      "collectionId": "ecard3",
      "collectionName": "Skyridge",
      "ligaSetCode": "SK",
      "tcgdexSetId": "ecard3",
      "number": "119",
      "printedTotal": "144",
      "imageUrl": "https://assets.tcgdex.net/en/ecard/ecard3/119",
      "types": [],
      "rarity": ""
    },
    {
      "id": "ecard3-120",
      "name": "Relic Hunter",
      "searchName": "Relic Hunter",
      "collectionId": "ecard3",
      "collectionName": "Skyridge",
      "ligaSetCode": "SK",
      "tcgdexSetId": "ecard3",
      "number": "120",
      "printedTotal": "144",
      "imageUrl": "https://assets.tcgdex.net/en/ecard/ecard3/120",
      "types": [],
      "rarity": ""
    },
    {
      "id": "ecard3-121",
      "name": "Apricorn Maker",
      "searchName": "Apricorn Maker",
      "collectionId": "ecard3",
      "collectionName": "Skyridge",
      "ligaSetCode": "SK",
      "tcgdexSetId": "ecard3",
      "number": "121",
      "printedTotal": "144",
      "imageUrl": "https://assets.tcgdex.net/en/ecard/ecard3/121",
      "types": [],
      "rarity": ""
    },
    {
      "id": "ecard3-122",
      "name": "Crystal Shard",
      "searchName": "Crystal Shard",
      "collectionId": "ecard3",
      "collectionName": "Skyridge",
      "ligaSetCode": "SK",
      "tcgdexSetId": "ecard3",
      "number": "122",
      "printedTotal": "144",
      "imageUrl": "https://assets.tcgdex.net/en/ecard/ecard3/122",
      "types": [],
      "rarity": ""
    },
    {
      "id": "ecard3-123",
      "name": "Desert Shaman",
      "searchName": "Desert Shaman",
      "collectionId": "ecard3",
      "collectionName": "Skyridge",
      "ligaSetCode": "SK",
      "tcgdexSetId": "ecard3",
      "number": "123",
      "printedTotal": "144",
      "imageUrl": "https://assets.tcgdex.net/en/ecard/ecard3/123",
      "types": [],
      "rarity": ""
    },
    {
      "id": "ecard3-124",
      "name": "Fast Ball",
      "searchName": "Fast Ball",
      "collectionId": "ecard3",
      "collectionName": "Skyridge",
      "ligaSetCode": "SK",
      "tcgdexSetId": "ecard3",
      "number": "124",
      "printedTotal": "144",
      "imageUrl": "https://assets.tcgdex.net/en/ecard/ecard3/124",
      "types": [],
      "rarity": ""
    },
    {
      "id": "ecard3-125",
      "name": "Fisherman",
      "searchName": "Fisherman",
      "collectionId": "ecard3",
      "collectionName": "Skyridge",
      "ligaSetCode": "SK",
      "tcgdexSetId": "ecard3",
      "number": "125",
      "printedTotal": "144",
      "imageUrl": "https://assets.tcgdex.net/en/ecard/ecard3/125",
      "types": [],
      "rarity": ""
    },
    {
      "id": "ecard3-126",
      "name": "Friend Ball",
      "searchName": "Friend Ball",
      "collectionId": "ecard3",
      "collectionName": "Skyridge",
      "ligaSetCode": "SK",
      "tcgdexSetId": "ecard3",
      "number": "126",
      "printedTotal": "144",
      "imageUrl": "https://assets.tcgdex.net/en/ecard/ecard3/126",
      "types": [],
      "rarity": ""
    },
    {
      "id": "ecard3-127",
      "name": "Hyper Potion",
      "searchName": "Hyper Potion",
      "collectionId": "ecard3",
      "collectionName": "Skyridge",
      "ligaSetCode": "SK",
      "tcgdexSetId": "ecard3",
      "number": "127",
      "printedTotal": "144",
      "imageUrl": "https://assets.tcgdex.net/en/ecard/ecard3/127",
      "types": [],
      "rarity": ""
    },
    {
      "id": "ecard3-128",
      "name": "Lure Ball",
      "searchName": "Lure Ball",
      "collectionId": "ecard3",
      "collectionName": "Skyridge",
      "ligaSetCode": "SK",
      "tcgdexSetId": "ecard3",
      "number": "128",
      "printedTotal": "144",
      "imageUrl": "https://assets.tcgdex.net/en/ecard/ecard3/128",
      "types": [],
      "rarity": ""
    },
    {
      "id": "ecard3-129",
      "name": "Miracle Sphere Alpha",
      "searchName": "Miracle Sphere Alpha",
      "collectionId": "ecard3",
      "collectionName": "Skyridge",
      "ligaSetCode": "SK",
      "tcgdexSetId": "ecard3",
      "number": "129",
      "printedTotal": "144",
      "imageUrl": "https://assets.tcgdex.net/en/ecard/ecard3/129",
      "types": [],
      "rarity": ""
    },
    {
      "id": "ecard3-130",
      "name": "Miracle Sphere Beta",
      "searchName": "Miracle Sphere Beta",
      "collectionId": "ecard3",
      "collectionName": "Skyridge",
      "ligaSetCode": "SK",
      "tcgdexSetId": "ecard3",
      "number": "130",
      "printedTotal": "144",
      "imageUrl": "https://assets.tcgdex.net/en/ecard/ecard3/130",
      "types": [],
      "rarity": ""
    },
    {
      "id": "ecard3-131",
      "name": "Miracle Sphere Gamma",
      "searchName": "Miracle Sphere Gamma",
      "collectionId": "ecard3",
      "collectionName": "Skyridge",
      "ligaSetCode": "SK",
      "tcgdexSetId": "ecard3",
      "number": "131",
      "printedTotal": "144",
      "imageUrl": "https://assets.tcgdex.net/en/ecard/ecard3/131",
      "types": [],
      "rarity": ""
    },
    {
      "id": "ecard3-132",
      "name": "Mirage Stadium",
      "searchName": "Mirage Stadium",
      "collectionId": "ecard3",
      "collectionName": "Skyridge",
      "ligaSetCode": "SK",
      "tcgdexSetId": "ecard3",
      "number": "132",
      "printedTotal": "144",
      "imageUrl": "https://assets.tcgdex.net/en/ecard/ecard3/132",
      "types": [],
      "rarity": ""
    },
    {
      "id": "ecard3-133",
      "name": "Mystery Plate Alpha",
      "searchName": "Mystery Plate Alpha",
      "collectionId": "ecard3",
      "collectionName": "Skyridge",
      "ligaSetCode": "SK",
      "tcgdexSetId": "ecard3",
      "number": "133",
      "printedTotal": "144",
      "imageUrl": "https://assets.tcgdex.net/en/ecard/ecard3/133",
      "types": [],
      "rarity": ""
    },
    {
      "id": "ecard3-134",
      "name": "Mystery Plate Beta",
      "searchName": "Mystery Plate Beta",
      "collectionId": "ecard3",
      "collectionName": "Skyridge",
      "ligaSetCode": "SK",
      "tcgdexSetId": "ecard3",
      "number": "134",
      "printedTotal": "144",
      "imageUrl": "https://assets.tcgdex.net/en/ecard/ecard3/134",
      "types": [],
      "rarity": ""
    },
    {
      "id": "ecard3-135",
      "name": "Mystery Plate Gamma",
      "searchName": "Mystery Plate Gamma",
      "collectionId": "ecard3",
      "collectionName": "Skyridge",
      "ligaSetCode": "SK",
      "tcgdexSetId": "ecard3",
      "number": "135",
      "printedTotal": "144",
      "imageUrl": "https://assets.tcgdex.net/en/ecard/ecard3/135",
      "types": [],
      "rarity": ""
    },
    {
      "id": "ecard3-136",
      "name": "Mystery Plate Delta",
      "searchName": "Mystery Plate Delta",
      "collectionId": "ecard3",
      "collectionName": "Skyridge",
      "ligaSetCode": "SK",
      "tcgdexSetId": "ecard3",
      "number": "136",
      "printedTotal": "144",
      "imageUrl": "https://assets.tcgdex.net/en/ecard/ecard3/136",
      "types": [],
      "rarity": ""
    },
    {
      "id": "ecard3-137",
      "name": "Mystery Zone",
      "searchName": "Mystery Zone",
      "collectionId": "ecard3",
      "collectionName": "Skyridge",
      "ligaSetCode": "SK",
      "tcgdexSetId": "ecard3",
      "number": "137",
      "printedTotal": "144",
      "imageUrl": "https://assets.tcgdex.net/en/ecard/ecard3/137",
      "types": [],
      "rarity": ""
    },
    {
      "id": "ecard3-138",
      "name": "Oracle",
      "searchName": "Oracle",
      "collectionId": "ecard3",
      "collectionName": "Skyridge",
      "ligaSetCode": "SK",
      "tcgdexSetId": "ecard3",
      "number": "138",
      "printedTotal": "144",
      "imageUrl": "https://assets.tcgdex.net/en/ecard/ecard3/138",
      "types": [],
      "rarity": ""
    },
    {
      "id": "ecard3-139",
      "name": "Star Piece",
      "searchName": "Star Piece",
      "collectionId": "ecard3",
      "collectionName": "Skyridge",
      "ligaSetCode": "SK",
      "tcgdexSetId": "ecard3",
      "number": "139",
      "printedTotal": "144",
      "imageUrl": "https://assets.tcgdex.net/en/ecard/ecard3/139",
      "types": [],
      "rarity": ""
    },
    {
      "id": "ecard3-140",
      "name": "Underground Expedition",
      "searchName": "Underground Expedition",
      "collectionId": "ecard3",
      "collectionName": "Skyridge",
      "ligaSetCode": "SK",
      "tcgdexSetId": "ecard3",
      "number": "140",
      "printedTotal": "144",
      "imageUrl": "https://assets.tcgdex.net/en/ecard/ecard3/140",
      "types": [],
      "rarity": ""
    },
    {
      "id": "ecard3-141",
      "name": "Underground Lake",
      "searchName": "Underground Lake",
      "collectionId": "ecard3",
      "collectionName": "Skyridge",
      "ligaSetCode": "SK",
      "tcgdexSetId": "ecard3",
      "number": "141",
      "printedTotal": "144",
      "imageUrl": "https://assets.tcgdex.net/en/ecard/ecard3/141",
      "types": [],
      "rarity": ""
    },
    {
      "id": "ecard3-142",
      "name": "Bounce Energy",
      "searchName": "Bounce Energy",
      "collectionId": "ecard3",
      "collectionName": "Skyridge",
      "ligaSetCode": "SK",
      "tcgdexSetId": "ecard3",
      "number": "142",
      "printedTotal": "144",
      "imageUrl": "https://assets.tcgdex.net/en/ecard/ecard3/142",
      "types": [],
      "rarity": ""
    },
    {
      "id": "ecard3-143",
      "name": "Cyclone Energy",
      "searchName": "Cyclone Energy",
      "collectionId": "ecard3",
      "collectionName": "Skyridge",
      "ligaSetCode": "SK",
      "tcgdexSetId": "ecard3",
      "number": "143",
      "printedTotal": "144",
      "imageUrl": "https://assets.tcgdex.net/en/ecard/ecard3/143",
      "types": [],
      "rarity": ""
    },
    {
      "id": "ecard3-144",
      "name": "Retro Energy",
      "searchName": "Retro Energy",
      "collectionId": "ecard3",
      "collectionName": "Skyridge",
      "ligaSetCode": "SK",
      "tcgdexSetId": "ecard3",
      "number": "144",
      "printedTotal": "144",
      "imageUrl": "https://assets.tcgdex.net/en/ecard/ecard3/144",
      "types": [],
      "rarity": ""
    },
    {
      "id": "ecard3-145",
      "name": "Celebi",
      "searchName": "Celebi",
      "collectionId": "ecard3",
      "collectionName": "Skyridge",
      "ligaSetCode": "SK",
      "tcgdexSetId": "ecard3",
      "number": "145",
      "printedTotal": "144",
      "imageUrl": "https://assets.tcgdex.net/en/ecard/ecard3/145",
      "types": [],
      "rarity": ""
    },
    {
      "id": "ecard3-146",
      "name": "Charizard",
      "searchName": "Charizard",
      "collectionId": "ecard3",
      "collectionName": "Skyridge",
      "ligaSetCode": "SK",
      "tcgdexSetId": "ecard3",
      "number": "146",
      "printedTotal": "144",
      "imageUrl": "https://assets.tcgdex.net/en/ecard/ecard3/146",
      "types": [],
      "rarity": ""
    },
    {
      "id": "ecard3-147",
      "name": "Crobat",
      "searchName": "Crobat",
      "collectionId": "ecard3",
      "collectionName": "Skyridge",
      "ligaSetCode": "SK",
      "tcgdexSetId": "ecard3",
      "number": "147",
      "printedTotal": "144",
      "imageUrl": "https://assets.tcgdex.net/en/ecard/ecard3/147",
      "types": [],
      "rarity": ""
    },
    {
      "id": "ecard3-148",
      "name": "Golem",
      "searchName": "Golem",
      "collectionId": "ecard3",
      "collectionName": "Skyridge",
      "ligaSetCode": "SK",
      "tcgdexSetId": "ecard3",
      "number": "148",
      "printedTotal": "144",
      "imageUrl": "https://assets.tcgdex.net/en/ecard/ecard3/148",
      "types": [],
      "rarity": ""
    },
    {
      "id": "ecard3-149",
      "name": "Ho-oh",
      "searchName": "Ho-oh",
      "collectionId": "ecard3",
      "collectionName": "Skyridge",
      "ligaSetCode": "SK",
      "tcgdexSetId": "ecard3",
      "number": "149",
      "printedTotal": "144",
      "imageUrl": "https://assets.tcgdex.net/en/ecard/ecard3/149",
      "types": [],
      "rarity": ""
    },
    {
      "id": "ecard3-150",
      "name": "Kabutops",
      "searchName": "Kabutops",
      "collectionId": "ecard3",
      "collectionName": "Skyridge",
      "ligaSetCode": "SK",
      "tcgdexSetId": "ecard3",
      "number": "150",
      "printedTotal": "144",
      "imageUrl": "https://assets.tcgdex.net/en/ecard/ecard3/150",
      "types": [],
      "rarity": ""
    },
    {
      "id": "ecard3-H01",
      "name": "Alakazam",
      "searchName": "Alakazam",
      "collectionId": "ecard3",
      "collectionName": "Skyridge",
      "ligaSetCode": "SK",
      "tcgdexSetId": "ecard3",
      "number": "H01",
      "printedTotal": "H32",
      "types": [],
      "rarity": ""
    },
    {
      "id": "ecard3-H02",
      "name": "Arcanine",
      "searchName": "Arcanine",
      "collectionId": "ecard3",
      "collectionName": "Skyridge",
      "ligaSetCode": "SK",
      "tcgdexSetId": "ecard3",
      "number": "H02",
      "printedTotal": "H32",
      "types": [],
      "rarity": ""
    },
    {
      "id": "ecard3-H03",
      "name": "Articuno",
      "searchName": "Articuno",
      "collectionId": "ecard3",
      "collectionName": "Skyridge",
      "ligaSetCode": "SK",
      "tcgdexSetId": "ecard3",
      "number": "H03",
      "printedTotal": "H32",
      "types": [],
      "rarity": ""
    },
    {
      "id": "ecard3-H04",
      "name": "Beedrill",
      "searchName": "Beedrill",
      "collectionId": "ecard3",
      "collectionName": "Skyridge",
      "ligaSetCode": "SK",
      "tcgdexSetId": "ecard3",
      "number": "H04",
      "printedTotal": "H32",
      "types": [],
      "rarity": ""
    },
    {
      "id": "ecard3-H05",
      "name": "Crobat",
      "searchName": "Crobat",
      "collectionId": "ecard3",
      "collectionName": "Skyridge",
      "ligaSetCode": "SK",
      "tcgdexSetId": "ecard3",
      "number": "H05",
      "printedTotal": "H32",
      "types": [],
      "rarity": ""
    },
    {
      "id": "ecard3-H06",
      "name": "Dewgong",
      "searchName": "Dewgong",
      "collectionId": "ecard3",
      "collectionName": "Skyridge",
      "ligaSetCode": "SK",
      "tcgdexSetId": "ecard3",
      "number": "H06",
      "printedTotal": "H32",
      "types": [],
      "rarity": ""
    },
    {
      "id": "ecard3-H07",
      "name": "Flareon",
      "searchName": "Flareon",
      "collectionId": "ecard3",
      "collectionName": "Skyridge",
      "ligaSetCode": "SK",
      "tcgdexSetId": "ecard3",
      "number": "H07",
      "printedTotal": "H32",
      "types": [],
      "rarity": ""
    },
    {
      "id": "ecard3-H08",
      "name": "Forretress",
      "searchName": "Forretress",
      "collectionId": "ecard3",
      "collectionName": "Skyridge",
      "ligaSetCode": "SK",
      "tcgdexSetId": "ecard3",
      "number": "H08",
      "printedTotal": "H32",
      "types": [],
      "rarity": ""
    },
    {
      "id": "ecard3-H09",
      "name": "Gengar",
      "searchName": "Gengar",
      "collectionId": "ecard3",
      "collectionName": "Skyridge",
      "ligaSetCode": "SK",
      "tcgdexSetId": "ecard3",
      "number": "H09",
      "printedTotal": "H32",
      "types": [],
      "rarity": ""
    },
    {
      "id": "ecard3-H10",
      "name": "Gyarados",
      "searchName": "Gyarados",
      "collectionId": "ecard3",
      "collectionName": "Skyridge",
      "ligaSetCode": "SK",
      "tcgdexSetId": "ecard3",
      "number": "H10",
      "printedTotal": "H32",
      "types": [],
      "rarity": ""
    },
    {
      "id": "ecard3-H11",
      "name": "Houndoom",
      "searchName": "Houndoom",
      "collectionId": "ecard3",
      "collectionName": "Skyridge",
      "ligaSetCode": "SK",
      "tcgdexSetId": "ecard3",
      "number": "H11",
      "printedTotal": "H32",
      "types": [],
      "rarity": ""
    },
    {
      "id": "ecard3-H12",
      "name": "Jolteon",
      "searchName": "Jolteon",
      "collectionId": "ecard3",
      "collectionName": "Skyridge",
      "ligaSetCode": "SK",
      "tcgdexSetId": "ecard3",
      "number": "H12",
      "printedTotal": "H32",
      "types": [],
      "rarity": ""
    },
    {
      "id": "ecard3-H13",
      "name": "Kabutops",
      "searchName": "Kabutops",
      "collectionId": "ecard3",
      "collectionName": "Skyridge",
      "ligaSetCode": "SK",
      "tcgdexSetId": "ecard3",
      "number": "H13",
      "printedTotal": "H32",
      "types": [],
      "rarity": ""
    },
    {
      "id": "ecard3-H14",
      "name": "Ledian",
      "searchName": "Ledian",
      "collectionId": "ecard3",
      "collectionName": "Skyridge",
      "ligaSetCode": "SK",
      "tcgdexSetId": "ecard3",
      "number": "H14",
      "printedTotal": "H32",
      "types": [],
      "rarity": ""
    },
    {
      "id": "ecard3-H15",
      "name": "Machamp",
      "searchName": "Machamp",
      "collectionId": "ecard3",
      "collectionName": "Skyridge",
      "ligaSetCode": "SK",
      "tcgdexSetId": "ecard3",
      "number": "H15",
      "printedTotal": "H32",
      "types": [],
      "rarity": ""
    },
    {
      "id": "ecard3-H16",
      "name": "Magcargo",
      "searchName": "Magcargo",
      "collectionId": "ecard3",
      "collectionName": "Skyridge",
      "ligaSetCode": "SK",
      "tcgdexSetId": "ecard3",
      "number": "H16",
      "printedTotal": "H32",
      "types": [],
      "rarity": ""
    },
    {
      "id": "ecard3-H17",
      "name": "Magcargo",
      "searchName": "Magcargo",
      "collectionId": "ecard3",
      "collectionName": "Skyridge",
      "ligaSetCode": "SK",
      "tcgdexSetId": "ecard3",
      "number": "H17",
      "printedTotal": "H32",
      "types": [],
      "rarity": ""
    },
    {
      "id": "ecard3-H18",
      "name": "Magneton",
      "searchName": "Magneton",
      "collectionId": "ecard3",
      "collectionName": "Skyridge",
      "ligaSetCode": "SK",
      "tcgdexSetId": "ecard3",
      "number": "H18",
      "printedTotal": "H32",
      "types": [],
      "rarity": ""
    },
    {
      "id": "ecard3-H19",
      "name": "Magneton",
      "searchName": "Magneton",
      "collectionId": "ecard3",
      "collectionName": "Skyridge",
      "ligaSetCode": "SK",
      "tcgdexSetId": "ecard3",
      "number": "H19",
      "printedTotal": "H32",
      "types": [],
      "rarity": ""
    },
    {
      "id": "ecard3-H20",
      "name": "Moltres",
      "searchName": "Moltres",
      "collectionId": "ecard3",
      "collectionName": "Skyridge",
      "ligaSetCode": "SK",
      "tcgdexSetId": "ecard3",
      "number": "H20",
      "printedTotal": "H32",
      "types": [],
      "rarity": ""
    },
    {
      "id": "ecard3-H21",
      "name": "Nidoqueen",
      "searchName": "Nidoqueen",
      "collectionId": "ecard3",
      "collectionName": "Skyridge",
      "ligaSetCode": "SK",
      "tcgdexSetId": "ecard3",
      "number": "H21",
      "printedTotal": "H32",
      "types": [],
      "rarity": ""
    },
    {
      "id": "ecard3-H22",
      "name": "Piloswine",
      "searchName": "Piloswine",
      "collectionId": "ecard3",
      "collectionName": "Skyridge",
      "ligaSetCode": "SK",
      "tcgdexSetId": "ecard3",
      "number": "H22",
      "printedTotal": "H32",
      "types": [],
      "rarity": ""
    },
    {
      "id": "ecard3-H23",
      "name": "Politoed",
      "searchName": "Politoed",
      "collectionId": "ecard3",
      "collectionName": "Skyridge",
      "ligaSetCode": "SK",
      "tcgdexSetId": "ecard3",
      "number": "H23",
      "printedTotal": "H32",
      "types": [],
      "rarity": ""
    },
    {
      "id": "ecard3-H24",
      "name": "Poliwrath",
      "searchName": "Poliwrath",
      "collectionId": "ecard3",
      "collectionName": "Skyridge",
      "ligaSetCode": "SK",
      "tcgdexSetId": "ecard3",
      "number": "H24",
      "printedTotal": "H32",
      "types": [],
      "rarity": ""
    },
    {
      "id": "ecard3-H25",
      "name": "Raichu",
      "searchName": "Raichu",
      "collectionId": "ecard3",
      "collectionName": "Skyridge",
      "ligaSetCode": "SK",
      "tcgdexSetId": "ecard3",
      "number": "H25",
      "printedTotal": "H32",
      "types": [],
      "rarity": ""
    },
    {
      "id": "ecard3-H26",
      "name": "Raikou",
      "searchName": "Raikou",
      "collectionId": "ecard3",
      "collectionName": "Skyridge",
      "ligaSetCode": "SK",
      "tcgdexSetId": "ecard3",
      "number": "H26",
      "printedTotal": "H32",
      "types": [],
      "rarity": ""
    },
    {
      "id": "ecard3-H27",
      "name": "Rhydon",
      "searchName": "Rhydon",
      "collectionId": "ecard3",
      "collectionName": "Skyridge",
      "ligaSetCode": "SK",
      "tcgdexSetId": "ecard3",
      "number": "H27",
      "printedTotal": "H32",
      "types": [],
      "rarity": ""
    },
    {
      "id": "ecard3-H28",
      "name": "Starmie",
      "searchName": "Starmie",
      "collectionId": "ecard3",
      "collectionName": "Skyridge",
      "ligaSetCode": "SK",
      "tcgdexSetId": "ecard3",
      "number": "H28",
      "printedTotal": "H32",
      "types": [],
      "rarity": ""
    },
    {
      "id": "ecard3-H29",
      "name": "Steelix",
      "searchName": "Steelix",
      "collectionId": "ecard3",
      "collectionName": "Skyridge",
      "ligaSetCode": "SK",
      "tcgdexSetId": "ecard3",
      "number": "H29",
      "printedTotal": "H32",
      "types": [],
      "rarity": ""
    },
    {
      "id": "ecard3-H30",
      "name": "Umbreon",
      "searchName": "Umbreon",
      "collectionId": "ecard3",
      "collectionName": "Skyridge",
      "ligaSetCode": "SK",
      "tcgdexSetId": "ecard3",
      "number": "H30",
      "printedTotal": "H32",
      "types": [],
      "rarity": ""
    },
    {
      "id": "ecard3-H31",
      "name": "Vaporeon",
      "searchName": "Vaporeon",
      "collectionId": "ecard3",
      "collectionName": "Skyridge",
      "ligaSetCode": "SK",
      "tcgdexSetId": "ecard3",
      "number": "H31",
      "printedTotal": "H32",
      "types": [],
      "rarity": ""
    },
    {
      "id": "ecard3-H32",
      "name": "Xatu",
      "searchName": "Xatu",
      "collectionId": "ecard3",
      "collectionName": "Skyridge",
      "ligaSetCode": "SK",
      "tcgdexSetId": "ecard3",
      "number": "H32",
      "printedTotal": "H32",
      "types": [],
      "rarity": ""
    }
  ]
}
