{
  "id": "sv03.5",
  "name": "151",
  "shortName": "151",
  "serie": "Escarlate e Violeta",
  "releaseYear": 2023,
  "releaseDate": "2023-09-22",
  "cardCount": 207,
  "officialCount": 165,
  "ligaSetCode": "MEW",
  "tcgdexSetId": "sv03.5",
  "logoUrl": "https://assets.tcgdex.net/pt/sv/sv03.5/logo",
  "symbolUrl": "https://assets.tcgdex.net/univ/sv/sv03.5/symbol",
  "language": "pt",
  "hasPortugueseData": true,
  "cards": [
    {
      "id": "sv03.5-001",
      "name": "Bulbasaur",
      "searchName": "Bulbasaur",
      "collectionId": "sv03.5",
      "collectionName": "151",
      "ligaSetCode": "MEW",
      "tcgdexSetId": "sv03.5",
      "number": "001",
      "printedTotal": "165",
      "imageUrl": "https://assets.tcgdex.net/pt/sv/sv03.5/001",
      "types": [],
      "rarity": ""
    },
    {
      "id": "sv03.5-002",
      "name": "Ivysaur",
      "searchName": "Ivysaur",
      "collectionId": "sv03.5",
      "collectionName": "151",
      "ligaSetCode": "MEW",
      "tcgdexSetId": "sv03.5",
      "number": "002",
      "printedTotal": "165",
      "imageUrl": "https://assets.tcgdex.net/pt/sv/sv03.5/002",
      "types": [],
      "rarity": ""
    },
    {
      "id": "sv03.5-003",
      "name": "Venusaur ex",
      "searchName": "Venusaur ex",
      "collectionId": "sv03.5",
      "collectionName": "151",
      "ligaSetCode": "MEW",
      "tcgdexSetId": "sv03.5",
      "number": "003",
      "printedTotal": "165",
      "imageUrl": "https://assets.tcgdex.net/pt/sv/sv03.5/003",
      "types": [],
      "rarity": ""
    },
    {
      "id": "sv03.5-004",
      "name": "Charmander",
      "searchName": "Charmander",
      "collectionId": "sv03.5",
      "collectionName": "151",
      "ligaSetCode": "MEW",
      "tcgdexSetId": "sv03.5",
      "number": "004",
      "printedTotal": "165",
      "imageUrl": "https://assets.tcgdex.net/pt/sv/sv03.5/004",
      "types": [],
      "rarity": ""
    },
    {
      "id": "sv03.5-005",
      "name": "Charmeleon",
      "searchName": "Charmeleon",
      "collectionId": "sv03.5",
      "collectionName": "151",
      "ligaSetCode": "MEW",
      "tcgdexSetId": "sv03.5",
      "number": "005",
      "printedTotal": "165",
      "imageUrl": "https://assets.tcgdex.net/pt/sv/sv03.5/005",
      "types": [],
      "rarity": ""
    },
    {
      "id": "sv03.5-006",
      "name": "Charizard ex",
      "searchName": "Charizard ex",
      "collectionId": "sv03.5",
      "collectionName": "151",
      "ligaSetCode": "MEW",
      "tcgdexSetId": "sv03.5",
      "number": "006",
      "printedTotal": "165",
      "imageUrl": "https://assets.tcgdex.net/pt/sv/sv03.5/006",
      "types": [],
      "rarity": ""
    },
    {
      "id": "sv03.5-007",
      "name": "Squirtle",
      "searchName": "Squirtle",
      "collectionId": "sv03.5",
      "collectionName": "151",
      "ligaSetCode": "MEW",
      "tcgdexSetId": "sv03.5",
      "number": "007",
      "printedTotal": "165",
      "imageUrl": "https://assets.tcgdex.net/pt/sv/sv03.5/007",
      "types": [],
      "rarity": ""
    },
    {
      "id": "sv03.5-008",
      "name": "Wartortle",
      "searchName": "Wartortle",
      "collectionId": "sv03.5",
      "collectionName": "151",
      "ligaSetCode": "MEW",
      "tcgdexSetId": "sv03.5",
      "number": "008",
      "printedTotal": "165",
      "imageUrl": "https://assets.tcgdex.net/pt/sv/sv03.5/008",
      "types": [],
      "rarity": ""
    },
    {
      "id": "sv03.5-009",
      "name": "Blastoise ex",
      "searchName": "Blastoise ex",
      "collectionId": "sv03.5",
      "collectionName": "151",
      "ligaSetCode": "MEW",
      "tcgdexSetId": "sv03.5",
      "number": "009",
      "printedTotal": "165",
      "imageUrl": "https://assets.tcgdex.net/pt/sv/sv03.5/009",
      "types": [],
      "rarity": ""
    },
    {
      "id": "sv03.5-010",
      "name": "Caterpie",
      "searchName": "Caterpie",
      "collectionId": "sv03.5",
      "collectionName": "151",
      "ligaSetCode": "MEW",
      "tcgdexSetId": "sv03.5",
      "number": "010",
      "printedTotal": "165",
      "imageUrl": "https://assets.tcgdex.net/pt/sv/sv03.5/010",
      "types": [],
      "rarity": ""
    },
    {
      "id": "sv03.5-011",
      "name": "Metapod",
      "searchName": "Metapod",
      "collectionId": "sv03.5",
      "collectionName": "151",
      "ligaSetCode": "MEW",
      "tcgdexSetId": "sv03.5",
      "number": "011",
      "printedTotal": "165",
      "imageUrl": "https://assets.tcgdex.net/pt/sv/sv03.5/011",
      "types": [],
      "rarity": ""
    },
    {
      "id": "sv03.5-012",
      "name": "Butterfree",
      "searchName": "Butterfree",
      "collectionId": "sv03.5",
      "collectionName": "151",
      "ligaSetCode": "MEW",
      "tcgdexSetId": "sv03.5",
      "number": "012",
      "printedTotal": "165",
      "imageUrl": "https://assets.tcgdex.net/pt/sv/sv03.5/012",
      "types": [],
      "rarity": ""
    },
    {
      "id": "sv03.5-013",
      "name": "Weedle",
      "searchName": "Weedle",
      "collectionId": "sv03.5",
      "collectionName": "151",
      "ligaSetCode": "MEW",
      "tcgdexSetId": "sv03.5",
      "number": "013",
      "printedTotal": "165",
      "imageUrl": "https://assets.tcgdex.net/pt/sv/sv03.5/013",
      "types": [],
      "rarity": ""
    },
    {
      "id": "sv03.5-014",
      "name": "Kakuna",
      "searchName": "Kakuna",
      "collectionId": "sv03.5",
      "collectionName": "151",
      "ligaSetCode": "MEW",
      "tcgdexSetId": "sv03.5",
      "number": "014",
      "printedTotal": "165",
      "imageUrl": "https://assets.tcgdex.net/pt/sv/sv03.5/014",
      "types": [],
      "rarity": ""
    },
    {
      "id": "sv03.5-015",
      "name": "Beedrill",
      "searchName": "Beedrill",
      "collectionId": "sv03.5",
      "collectionName": "151",
      "ligaSetCode": "MEW",
      "tcgdexSetId": "sv03.5",
      "number": "015",
      "printedTotal": "165",
      "imageUrl": "https://assets.tcgdex.net/pt/sv/sv03.5/015",
      "types": [],
      "rarity": ""
    },
    {
      "id": "sv03.5-016",
      "name": "Pidgey",
      "searchName": "Pidgey",
      "collectionId": "sv03.5",
      "collectionName": "151",
      "ligaSetCode": "MEW",
      "tcgdexSetId": "sv03.5",
      "number": "016",
      "printedTotal": "165",
      "imageUrl": "https://assets.tcgdex.net/pt/sv/sv03.5/016",
      "types": [],
      "rarity": ""
    },
    {
      "id": "sv03.5-017",
      "name": "Pidgeotto",
      "searchName": "Pidgeotto",
      "collectionId": "sv03.5",
      "collectionName": "151",
      "ligaSetCode": "MEW",
      "tcgdexSetId": "sv03.5",
      "number": "017",
      "printedTotal": "165",
      "imageUrl": "https://assets.tcgdex.net/pt/sv/sv03.5/017",
      "types": [],
      "rarity": ""
    },
    {
      "id": "sv03.5-018",
      "name": "Pidgeot",
      "searchName": "Pidgeot",
      "collectionId": "sv03.5",
      "collectionName": "151",
      "ligaSetCode": "MEW",
      "tcgdexSetId": "sv03.5",
      "number": "018",
      "printedTotal": "165",
      "imageUrl": "https://assets.tcgdex.net/pt/sv/sv03.5/018",
      "types": [],
      "rarity": ""
    },
    {
      "id": "sv03.5-019",
      "name": "Rattata",
      "searchName": "Rattata",
      "collectionId": "sv03.5",
      "collectionName": "151",
      "ligaSetCode": "MEW",
      "tcgdexSetId": "sv03.5",
      "number": "019",
      "printedTotal": "165",
      "imageUrl": "https://assets.tcgdex.net/pt/sv/sv03.5/019",
      "types": [],
      "rarity": ""
    },
    {
      "id": "sv03.5-020",
      "name": "Raticate",
      "searchName": "Raticate",
      "collectionId": "sv03.5",
      "collectionName": "151",
      "ligaSetCode": "MEW",
      "tcgdexSetId": "sv03.5",
      "number": "020",
      "printedTotal": "165",
      "imageUrl": "https://assets.tcgdex.net/pt/sv/sv03.5/020",
      "types": [],
      "rarity": ""
    },
    {
      "id": "sv03.5-021",
      "name": "Spearow",
      "searchName": "Spearow",
      "collectionId": "sv03.5",
      "collectionName": "151",
      "ligaSetCode": "MEW",
      "tcgdexSetId": "sv03.5",
      "number": "021",
      "printedTotal": "165",
      "imageUrl": "https://assets.tcgdex.net/pt/sv/sv03.5/021",
      "types": [],
      "rarity": ""
    },
    {
      "id": "sv03.5-022",
      "name": "Fearow",
      "searchName": "Fearow",
      "collectionId": "sv03.5",
      "collectionName": "151",
      "ligaSetCode": "MEW",
      "tcgdexSetId": "sv03.5",
      "number": "022",
      "printedTotal": "165",
      "imageUrl": "https://assets.tcgdex.net/pt/sv/sv03.5/022",
      "types": [],
      "rarity": ""
    },
    {
      "id": "sv03.5-023",
      "name": "Ekans",
      "searchName": "Ekans",
      "collectionId": "sv03.5",
      "collectionName": "151",
      "ligaSetCode": "MEW",
      "tcgdexSetId": "sv03.5",
      "number": "023",
      "printedTotal": "165",
      "imageUrl": "https://assets.tcgdex.net/pt/sv/sv03.5/023",
      "types": [],
      "rarity": ""
    },
    {
      "id": "sv03.5-024",
      "name": "Arbok ex",
      "searchName": "Arbok ex",
      "collectionId": "sv03.5",
      "collectionName": "151",
      "ligaSetCode": "MEW",
      "tcgdexSetId": "sv03.5",
      "number": "024",
      "printedTotal": "165",
      "imageUrl": "https://assets.tcgdex.net/pt/sv/sv03.5/024",
      "types": [],
      "rarity": ""
    },
    {
      "id": "sv03.5-025",
      "name": "Pikachu",
      "searchName": "Pikachu",
      "collectionId": "sv03.5",
      "collectionName": "151",
      "ligaSetCode": "MEW",
      "tcgdexSetId": "sv03.5",
      "number": "025",
      "printedTotal": "165",
      "imageUrl": "https://assets.tcgdex.net/pt/sv/sv03.5/025",
      "types": [],
      "rarity": ""
    },
    {
      "id": "sv03.5-026",
      "name": "Raichu",
      "searchName": "Raichu",
      "collectionId": "sv03.5",
      "collectionName": "151",
      "ligaSetCode": "MEW",
      "tcgdexSetId": "sv03.5",
      "number": "026",
      "printedTotal": "165",
      "imageUrl": "https://assets.tcgdex.net/pt/sv/sv03.5/026",
      "types": [],
      "rarity": ""
    },
    {
      "id": "sv03.5-027",
      "name": "Sandshrew",
      "searchName": "Sandshrew",
      "collectionId": "sv03.5",
      "collectionName": "151",
      "ligaSetCode": "MEW",
      "tcgdexSetId": "sv03.5",
      "number": "027",
      "printedTotal": "165",
      "imageUrl": "https://assets.tcgdex.net/pt/sv/sv03.5/027",
      "types": [],
      "rarity": ""
    },
    {
      "id": "sv03.5-028",
      "name": "Sandslash",
      "searchName": "Sandslash",
      "collectionId": "sv03.5",
      "collectionName": "151",
      "ligaSetCode": "MEW",
      "tcgdexSetId": "sv03.5",
      "number": "028",
      "printedTotal": "165",
      "imageUrl": "https://assets.tcgdex.net/pt/sv/sv03.5/028",
      "types": [],
      "rarity": ""
    },
    {
      "id": "sv03.5-029",
      "name": "Nidoran♀",
      "searchName": "Nidoran♀",
      "collectionId": "sv03.5",
      "collectionName": "151",
      "ligaSetCode": "MEW",
      "tcgdexSetId": "sv03.5",
      "number": "029",
      "printedTotal": "165",
      "imageUrl": "https://assets.tcgdex.net/pt/sv/sv03.5/029",
      "types": [],
      "rarity": ""
    },
    {
      "id": "sv03.5-030",
      "name": "Nidorina",
      "searchName": "Nidorina",
      "collectionId": "sv03.5",
      "collectionName": "151",
      "ligaSetCode": "MEW",
      "tcgdexSetId": "sv03.5",
      "number": "030",
      "printedTotal": "165",
      "imageUrl": "https://assets.tcgdex.net/pt/sv/sv03.5/030",
      "types": [],
      "rarity": ""
    },
    {
      "id": "sv03.5-031",
      "name": "Nidoqueen",
      "searchName": "Nidoqueen",
      "collectionId": "sv03.5",
      "collectionName": "151",
      "ligaSetCode": "MEW",
      "tcgdexSetId": "sv03.5",
      "number": "031",
      "printedTotal": "165",
      "imageUrl": "https://assets.tcgdex.net/pt/sv/sv03.5/031",
      "types": [],
      "rarity": ""
    },
    {
      "id": "sv03.5-032",
      "name": "Nidoran♂",
      "searchName": "Nidoran♂",
      "collectionId": "sv03.5",
      "collectionName": "151",
      "ligaSetCode": "MEW",
      "tcgdexSetId": "sv03.5",
      "number": "032",
      "printedTotal": "165",
      "imageUrl": "https://assets.tcgdex.net/pt/sv/sv03.5/032",
      "types": [],
      "rarity": ""
    },
    {
      "id": "sv03.5-033",
      "name": "Nidorino",
      "searchName": "Nidorino",
      "collectionId": "sv03.5",
      "collectionName": "151",
      "ligaSetCode": "MEW",
      "tcgdexSetId": "sv03.5",
      "number": "033",
      "printedTotal": "165",
      "imageUrl": "https://assets.tcgdex.net/pt/sv/sv03.5/033",
      "types": [],
      "rarity": ""
    },
    {
      "id": "sv03.5-034",
      "name": "Nidoking",
      "searchName": "Nidoking",
      "collectionId": "sv03.5",
      "collectionName": "151",
      "ligaSetCode": "MEW",
      "tcgdexSetId": "sv03.5",
      "number": "034",
      "printedTotal": "165",
      "imageUrl": "https://assets.tcgdex.net/pt/sv/sv03.5/034",
      "types": [],
      "rarity": ""
    },
    {
      "id": "sv03.5-035",
      "name": "Clefairy",
      "searchName": "Clefairy",
      "collectionId": "sv03.5",
      "collectionName": "151",
      "ligaSetCode": "MEW",
      "tcgdexSetId": "sv03.5",
      "number": "035",
      "printedTotal": "165",
      "imageUrl": "https://assets.tcgdex.net/pt/sv/sv03.5/035",
      "types": [],
      "rarity": ""
    },
    {
      "id": "sv03.5-036",
      "name": "Clefable",
      "searchName": "Clefable",
      "collectionId": "sv03.5",
      "collectionName": "151",
      "ligaSetCode": "MEW",
      "tcgdexSetId": "sv03.5",
      "number": "036",
      "printedTotal": "165",
      "imageUrl": "https://assets.tcgdex.net/pt/sv/sv03.5/036",
      "types": [],
      "rarity": ""
    },
    {
      "id": "sv03.5-037",
      "name": "Vulpix",
      "searchName": "Vulpix",
      "collectionId": "sv03.5",
      "collectionName": "151",
      "ligaSetCode": "MEW",
      "tcgdexSetId": "sv03.5",
      "number": "037",
      "printedTotal": "165",
      "imageUrl": "https://assets.tcgdex.net/pt/sv/sv03.5/037",
      "types": [],
      "rarity": ""
    },
    {
      "id": "sv03.5-038",
      "name": "Ninetales ex",
      "searchName": "Ninetales ex",
      "collectionId": "sv03.5",
      "collectionName": "151",
      "ligaSetCode": "MEW",
      "tcgdexSetId": "sv03.5",
      "number": "038",
      "printedTotal": "165",
      "imageUrl": "https://assets.tcgdex.net/pt/sv/sv03.5/038",
      "types": [],
      "rarity": ""
    },
    {
      "id": "sv03.5-039",
      "name": "Jigglypuff",
      "searchName": "Jigglypuff",
      "collectionId": "sv03.5",
      "collectionName": "151",
      "ligaSetCode": "MEW",
      "tcgdexSetId": "sv03.5",
      "number": "039",
      "printedTotal": "165",
      "imageUrl": "https://assets.tcgdex.net/pt/sv/sv03.5/039",
      "types": [],
      "rarity": ""
    },
    {
      "id": "sv03.5-040",
      "name": "Wigglytuff ex",
      "searchName": "Wigglytuff ex",
      "collectionId": "sv03.5",
      "collectionName": "151",
      "ligaSetCode": "MEW",
      "tcgdexSetId": "sv03.5",
      "number": "040",
      "printedTotal": "165",
      "imageUrl": "https://assets.tcgdex.net/pt/sv/sv03.5/040",
      "types": [],
      "rarity": ""
    },
    {
      "id": "sv03.5-041",
      "name": "Zubat",
      "searchName": "Zubat",
      "collectionId": "sv03.5",
      "collectionName": "151",
      "ligaSetCode": "MEW",
      "tcgdexSetId": "sv03.5",
      "number": "041",
      "printedTotal": "165",
      "imageUrl": "https://assets.tcgdex.net/pt/sv/sv03.5/041",
      "types": [],
      "rarity": ""
    },
    {
      "id": "sv03.5-042",
      "name": "Golbat",
      "searchName": "Golbat",
      "collectionId": "sv03.5",
      "collectionName": "151",
      "ligaSetCode": "MEW",
      "tcgdexSetId": "sv03.5",
      "number": "042",
      "printedTotal": "165",
      "imageUrl": "https://assets.tcgdex.net/pt/sv/sv03.5/042",
      "types": [],
      "rarity": ""
    },
    {
      "id": "sv03.5-043",
      "name": "Oddish",
      "searchName": "Oddish",
      "collectionId": "sv03.5",
      "collectionName": "151",
      "ligaSetCode": "MEW",
      "tcgdexSetId": "sv03.5",
      "number": "043",
      "printedTotal": "165",
      "imageUrl": "https://assets.tcgdex.net/pt/sv/sv03.5/043",
      "types": [],
      "rarity": ""
    },
    {
      "id": "sv03.5-044",
      "name": "Gloom",
      "searchName": "Gloom",
      "collectionId": "sv03.5",
      "collectionName": "151",
      "ligaSetCode": "MEW",
      "tcgdexSetId": "sv03.5",
      "number": "044",
      "printedTotal": "165",
      "imageUrl": "https://assets.tcgdex.net/pt/sv/sv03.5/044",
      "types": [],
      "rarity": ""
    },
    {
      "id": "sv03.5-045",
      "name": "Vileplume",
      "searchName": "Vileplume",
      "collectionId": "sv03.5",
      "collectionName": "151",
      "ligaSetCode": "MEW",
      "tcgdexSetId": "sv03.5",
      "number": "045",
      "printedTotal": "165",
      "imageUrl": "https://assets.tcgdex.net/pt/sv/sv03.5/045",
      "types": [],
      "rarity": ""
    },
    {
      "id": "sv03.5-046",
      "name": "Paras",
      "searchName": "Paras",
      "collectionId": "sv03.5",
      "collectionName": "151",
      "ligaSetCode": "MEW",
      "tcgdexSetId": "sv03.5",
      "number": "046",
      "printedTotal": "165",
      "imageUrl": "https://assets.tcgdex.net/pt/sv/sv03.5/046",
      "types": [],
      "rarity": ""
    },
    {
      "id": "sv03.5-047",
      "name": "Parasect",
      "searchName": "Parasect",
      "collectionId": "sv03.5",
      "collectionName": "151",
      "ligaSetCode": "MEW",
      "tcgdexSetId": "sv03.5",
      "number": "047",
      "printedTotal": "165",
      "imageUrl": "https://assets.tcgdex.net/pt/sv/sv03.5/047",
      "types": [],
      "rarity": ""
    },
    {
      "id": "sv03.5-048",
      "name": "Venonat",
      "searchName": "Venonat",
      "collectionId": "sv03.5",
      "collectionName": "151",
      "ligaSetCode": "MEW",
      "tcgdexSetId": "sv03.5",
      "number": "048",
      "printedTotal": "165",
      "imageUrl": "https://assets.tcgdex.net/pt/sv/sv03.5/048",
      "types": [],
      "rarity": ""
    },
    {
      "id": "sv03.5-049",
      "name": "Venomoth",
      "searchName": "Venomoth",
      "collectionId": "sv03.5",
      "collectionName": "151",
      "ligaSetCode": "MEW",
      "tcgdexSetId": "sv03.5",
      "number": "049",
      "printedTotal": "165",
      "imageUrl": "https://assets.tcgdex.net/pt/sv/sv03.5/049",
      "types": [],
      "rarity": ""
    },
    {
      "id": "sv03.5-050",
      "name": "Diglett",
      "searchName": "Diglett",
      "collectionId": "sv03.5",
      "collectionName": "151",
      "ligaSetCode": "MEW",
      "tcgdexSetId": "sv03.5",
      "number": "050",
      "printedTotal": "165",
      "imageUrl": "https://assets.tcgdex.net/pt/sv/sv03.5/050",
      "types": [],
      "rarity": ""
    },
    {
      "id": "sv03.5-051",
      "name": "Dugtrio",
      "searchName": "Dugtrio",
      "collectionId": "sv03.5",
      "collectionName": "151",
      "ligaSetCode": "MEW",
      "tcgdexSetId": "sv03.5",
      "number": "051",
      "printedTotal": "165",
      "imageUrl": "https://assets.tcgdex.net/pt/sv/sv03.5/051",
      "types": [],
      "rarity": ""
    },
    {
      "id": "sv03.5-052",
      "name": "Meowth",
      "searchName": "Meowth",
      "collectionId": "sv03.5",
      "collectionName": "151",
      "ligaSetCode": "MEW",
      "tcgdexSetId": "sv03.5",
      "number": "052",
      "printedTotal": "165",
      "imageUrl": "https://assets.tcgdex.net/pt/sv/sv03.5/052",
      "types": [],
      "rarity": ""
    },
    {
      "id": "sv03.5-053",
      "name": "Persian",
      "searchName": "Persian",
      "collectionId": "sv03.5",
      "collectionName": "151",
      "ligaSetCode": "MEW",
      "tcgdexSetId": "sv03.5",
      "number": "053",
      "printedTotal": "165",
      "imageUrl": "https://assets.tcgdex.net/pt/sv/sv03.5/053",
      "types": [],
      "rarity": ""
    },
    {
      "id": "sv03.5-054",
      "name": "Psyduck",
      "searchName": "Psyduck",
      "collectionId": "sv03.5",
      "collectionName": "151",
      "ligaSetCode": "MEW",
      "tcgdexSetId": "sv03.5",
      "number": "054",
      "printedTotal": "165",
      "imageUrl": "https://assets.tcgdex.net/pt/sv/sv03.5/054",
      "types": [],
      "rarity": ""
    },
    {
      "id": "sv03.5-055",
      "name": "Golduck",
      "searchName": "Golduck",
      "collectionId": "sv03.5",
      "collectionName": "151",
      "ligaSetCode": "MEW",
      "tcgdexSetId": "sv03.5",
      "number": "055",
      "printedTotal": "165",
      "imageUrl": "https://assets.tcgdex.net/pt/sv/sv03.5/055",
      "types": [],
      "rarity": ""
    },
    {
      "id": "sv03.5-056",
      "name": "Mankey",
      "searchName": "Mankey",
      "collectionId": "sv03.5",
      "collectionName": "151",
      "ligaSetCode": "MEW",
      "tcgdexSetId": "sv03.5",
      "number": "056",
      "printedTotal": "165",
      "imageUrl": "https://assets.tcgdex.net/pt/sv/sv03.5/056",
      "types": [],
      "rarity": ""
    },
    {
      "id": "sv03.5-057",
      "name": "Primeape",
      "searchName": "Primeape",
      "collectionId": "sv03.5",
      "collectionName": "151",
      "ligaSetCode": "MEW",
      "tcgdexSetId": "sv03.5",
      "number": "057",
      "printedTotal": "165",
      "imageUrl": "https://assets.tcgdex.net/pt/sv/sv03.5/057",
      "types": [],
      "rarity": ""
    },
    {
      "id": "sv03.5-058",
      "name": "Growlithe",
      "searchName": "Growlithe",
      "collectionId": "sv03.5",
      "collectionName": "151",
      "ligaSetCode": "MEW",
      "tcgdexSetId": "sv03.5",
      "number": "058",
      "printedTotal": "165",
      "imageUrl": "https://assets.tcgdex.net/pt/sv/sv03.5/058",
      "types": [],
      "rarity": ""
    },
    {
      "id": "sv03.5-059",
      "name": "Arcanine",
      "searchName": "Arcanine",
      "collectionId": "sv03.5",
      "collectionName": "151",
      "ligaSetCode": "MEW",
      "tcgdexSetId": "sv03.5",
      "number": "059",
      "printedTotal": "165",
      "imageUrl": "https://assets.tcgdex.net/pt/sv/sv03.5/059",
      "types": [],
      "rarity": ""
    },
    {
      "id": "sv03.5-060",
      "name": "Poliwag",
      "searchName": "Poliwag",
      "collectionId": "sv03.5",
      "collectionName": "151",
      "ligaSetCode": "MEW",
      "tcgdexSetId": "sv03.5",
      "number": "060",
      "printedTotal": "165",
      "imageUrl": "https://assets.tcgdex.net/pt/sv/sv03.5/060",
      "types": [],
      "rarity": ""
    },
    {
      "id": "sv03.5-061",
      "name": "Poliwhirl",
      "searchName": "Poliwhirl",
      "collectionId": "sv03.5",
      "collectionName": "151",
      "ligaSetCode": "MEW",
      "tcgdexSetId": "sv03.5",
      "number": "061",
      "printedTotal": "165",
      "imageUrl": "https://assets.tcgdex.net/pt/sv/sv03.5/061",
      "types": [],
      "rarity": ""
    },
    {
      "id": "sv03.5-062",
      "name": "Poliwrath",
      "searchName": "Poliwrath",
      "collectionId": "sv03.5",
      "collectionName": "151",
      "ligaSetCode": "MEW",
      "tcgdexSetId": "sv03.5",
      "number": "062",
      "printedTotal": "165",
      "imageUrl": "https://assets.tcgdex.net/pt/sv/sv03.5/062",
      "types": [],
      "rarity": ""
    },
    {
      "id": "sv03.5-063",
      "name": "Abra",
      "searchName": "Abra",
      "collectionId": "sv03.5",
      "collectionName": "151",
      "ligaSetCode": "MEW",
      "tcgdexSetId": "sv03.5",
      "number": "063",
      "printedTotal": "165",
      "imageUrl": "https://assets.tcgdex.net/pt/sv/sv03.5/063",
      "types": [],
      "rarity": ""
    },
    {
      "id": "sv03.5-064",
      "name": "Kadabra",
      "searchName": "Kadabra",
      "collectionId": "sv03.5",
      "collectionName": "151",
      "ligaSetCode": "MEW",
      "tcgdexSetId": "sv03.5",
      "number": "064",
      "printedTotal": "165",
      "imageUrl": "https://assets.tcgdex.net/pt/sv/sv03.5/064",
      "types": [],
      "rarity": ""
    },
    {
      "id": "sv03.5-065",
      "name": "Alakazam ex",
      "searchName": "Alakazam ex",
      "collectionId": "sv03.5",
      "collectionName": "151",
      "ligaSetCode": "MEW",
      "tcgdexSetId": "sv03.5",
      "number": "065",
      "printedTotal": "165",
      "imageUrl": "https://assets.tcgdex.net/pt/sv/sv03.5/065",
      "types": [],
      "rarity": ""
    },
    {
      "id": "sv03.5-066",
      "name": "Machop",
      "searchName": "Machop",
      "collectionId": "sv03.5",
      "collectionName": "151",
      "ligaSetCode": "MEW",
      "tcgdexSetId": "sv03.5",
      "number": "066",
      "printedTotal": "165",
      "imageUrl": "https://assets.tcgdex.net/pt/sv/sv03.5/066",
      "types": [],
      "rarity": ""
    },
    {
      "id": "sv03.5-067",
      "name": "Machoke",
      "searchName": "Machoke",
      "collectionId": "sv03.5",
      "collectionName": "151",
      "ligaSetCode": "MEW",
      "tcgdexSetId": "sv03.5",
      "number": "067",
      "printedTotal": "165",
      "imageUrl": "https://assets.tcgdex.net/pt/sv/sv03.5/067",
      "types": [],
      "rarity": ""
    },
    {
      "id": "sv03.5-068",
      "name": "Machamp",
      "searchName": "Machamp",
      "collectionId": "sv03.5",
      "collectionName": "151",
      "ligaSetCode": "MEW",
      "tcgdexSetId": "sv03.5",
      "number": "068",
      "printedTotal": "165",
      "imageUrl": "https://assets.tcgdex.net/pt/sv/sv03.5/068",
      "types": [],
      "rarity": ""
    },
    {
      "id": "sv03.5-069",
      "name": "Bellsprout",
      "searchName": "Bellsprout",
      "collectionId": "sv03.5",
      "collectionName": "151",
      "ligaSetCode": "MEW",
      "tcgdexSetId": "sv03.5",
      "number": "069",
      "printedTotal": "165",
      "imageUrl": "https://assets.tcgdex.net/pt/sv/sv03.5/069",
      "types": [],
      "rarity": ""
    },
    {
      "id": "sv03.5-070",
      "name": "Weepinbell",
      "searchName": "Weepinbell",
      "collectionId": "sv03.5",
      "collectionName": "151",
      "ligaSetCode": "MEW",
      "tcgdexSetId": "sv03.5",
      "number": "070",
      "printedTotal": "165",
      "imageUrl": "https://assets.tcgdex.net/pt/sv/sv03.5/070",
      "types": [],
      "rarity": ""
    },
    {
      "id": "sv03.5-071",
      "name": "Victreebel",
      "searchName": "Victreebel",
      "collectionId": "sv03.5",
      "collectionName": "151",
      "ligaSetCode": "MEW",
      "tcgdexSetId": "sv03.5",
      "number": "071",
      "printedTotal": "165",
      "imageUrl": "https://assets.tcgdex.net/pt/sv/sv03.5/071",
      "types": [],
      "rarity": ""
    },
    {
      "id": "sv03.5-072",
      "name": "Tentacool",
      "searchName": "Tentacool",
      "collectionId": "sv03.5",
      "collectionName": "151",
      "ligaSetCode": "MEW",
      "tcgdexSetId": "sv03.5",
      "number": "072",
      "printedTotal": "165",
      "imageUrl": "https://assets.tcgdex.net/pt/sv/sv03.5/072",
      "types": [],
      "rarity": ""
    },
    {
      "id": "sv03.5-073",
      "name": "Tentacruel",
      "searchName": "Tentacruel",
      "collectionId": "sv03.5",
      "collectionName": "151",
      "ligaSetCode": "MEW",
      "tcgdexSetId": "sv03.5",
      "number": "073",
      "printedTotal": "165",
      "imageUrl": "https://assets.tcgdex.net/pt/sv/sv03.5/073",
      "types": [],
      "rarity": ""
    },
    {
      "id": "sv03.5-074",
      "name": "Geodude",
      "searchName": "Geodude",
      "collectionId": "sv03.5",
      "collectionName": "151",
      "ligaSetCode": "MEW",
      "tcgdexSetId": "sv03.5",
      "number": "074",
      "printedTotal": "165",
      "imageUrl": "https://assets.tcgdex.net/pt/sv/sv03.5/074",
      "types": [],
      "rarity": ""
    },
    {
      "id": "sv03.5-075",
      "name": "Graveler",
      "searchName": "Graveler",
      "collectionId": "sv03.5",
      "collectionName": "151",
      "ligaSetCode": "MEW",
      "tcgdexSetId": "sv03.5",
      "number": "075",
      "printedTotal": "165",
      "imageUrl": "https://assets.tcgdex.net/pt/sv/sv03.5/075",
      "types": [],
      "rarity": ""
    },
    {
      "id": "sv03.5-076",
      "name": "Golem ex",
      "searchName": "Golem ex",
      "collectionId": "sv03.5",
      "collectionName": "151",
      "ligaSetCode": "MEW",
      "tcgdexSetId": "sv03.5",
      "number": "076",
      "printedTotal": "165",
      "imageUrl": "https://assets.tcgdex.net/pt/sv/sv03.5/076",
      "types": [],
      "rarity": ""
    },
    {
      "id": "sv03.5-077",
      "name": "Ponyta",
      "searchName": "Ponyta",
      "collectionId": "sv03.5",
      "collectionName": "151",
      "ligaSetCode": "MEW",
      "tcgdexSetId": "sv03.5",
      "number": "077",
      "printedTotal": "165",
      "imageUrl": "https://assets.tcgdex.net/pt/sv/sv03.5/077",
      "types": [],
      "rarity": ""
    },
    {
      "id": "sv03.5-078",
      "name": "Rapidash",
      "searchName": "Rapidash",
      "collectionId": "sv03.5",
      "collectionName": "151",
      "ligaSetCode": "MEW",
      "tcgdexSetId": "sv03.5",
      "number": "078",
      "printedTotal": "165",
      "imageUrl": "https://assets.tcgdex.net/pt/sv/sv03.5/078",
      "types": [],
      "rarity": ""
    },
    {
      "id": "sv03.5-079",
      "name": "Slowpoke",
      "searchName": "Slowpoke",
      "collectionId": "sv03.5",
      "collectionName": "151",
      "ligaSetCode": "MEW",
      "tcgdexSetId": "sv03.5",
      "number": "079",
      "printedTotal": "165",
      "imageUrl": "https://assets.tcgdex.net/pt/sv/sv03.5/079",
      "types": [],
      "rarity": ""
    },
    {
      "id": "sv03.5-080",
      "name": "Slowbro",
      "searchName": "Slowbro",
      "collectionId": "sv03.5",
      "collectionName": "151",
      "ligaSetCode": "MEW",
      "tcgdexSetId": "sv03.5",
      "number": "080",
      "printedTotal": "165",
      "imageUrl": "https://assets.tcgdex.net/pt/sv/sv03.5/080",
      "types": [],
      "rarity": ""
    },
    {
      "id": "sv03.5-081",
      "name": "Magnemite",
      "searchName": "Magnemite",
      "collectionId": "sv03.5",
      "collectionName": "151",
      "ligaSetCode": "MEW",
      "tcgdexSetId": "sv03.5",
      "number": "081",
      "printedTotal": "165",
      "imageUrl": "https://assets.tcgdex.net/pt/sv/sv03.5/081",
      "types": [],
      "rarity": ""
    },
    {
      "id": "sv03.5-082",
      "name": "Magneton",
      "searchName": "Magneton",
      "collectionId": "sv03.5",
      "collectionName": "151",
      "ligaSetCode": "MEW",
      "tcgdexSetId": "sv03.5",
      "number": "082",
      "printedTotal": "165",
      "imageUrl": "https://assets.tcgdex.net/pt/sv/sv03.5/082",
      "types": [],
      "rarity": ""
    },
    {
      "id": "sv03.5-083",
      "name": "Farfetch'd",
      "searchName": "Farfetch'd",
      "collectionId": "sv03.5",
      "collectionName": "151",
      "ligaSetCode": "MEW",
      "tcgdexSetId": "sv03.5",
      "number": "083",
      "printedTotal": "165",
      "imageUrl": "https://assets.tcgdex.net/pt/sv/sv03.5/083",
      "types": [],
      "rarity": ""
    },
    {
      "id": "sv03.5-084",
      "name": "Doduo",
      "searchName": "Doduo",
      "collectionId": "sv03.5",
      "collectionName": "151",
      "ligaSetCode": "MEW",
      "tcgdexSetId": "sv03.5",
      "number": "084",
      "printedTotal": "165",
      "imageUrl": "https://assets.tcgdex.net/pt/sv/sv03.5/084",
      "types": [],
      "rarity": ""
    },
    {
      "id": "sv03.5-085",
      "name": "Dodrio",
      "searchName": "Dodrio",
      "collectionId": "sv03.5",
      "collectionName": "151",
      "ligaSetCode": "MEW",
      "tcgdexSetId": "sv03.5",
      "number": "085",
      "printedTotal": "165",
      "imageUrl": "https://assets.tcgdex.net/pt/sv/sv03.5/085",
      "types": [],
      "rarity": ""
    },
    {
      "id": "sv03.5-086",
      "name": "Seel",
      "searchName": "Seel",
      "collectionId": "sv03.5",
      "collectionName": "151",
      "ligaSetCode": "MEW",
      "tcgdexSetId": "sv03.5",
      "number": "086",
      "printedTotal": "165",
      "imageUrl": "https://assets.tcgdex.net/pt/sv/sv03.5/086",
      "types": [],
      "rarity": ""
    },
    {
      "id": "sv03.5-087",
      "name": "Dewgong",
      "searchName": "Dewgong",
      "collectionId": "sv03.5",
      "collectionName": "151",
      "ligaSetCode": "MEW",
      "tcgdexSetId": "sv03.5",
      "number": "087",
      "printedTotal": "165",
      "imageUrl": "https://assets.tcgdex.net/pt/sv/sv03.5/087",
      "types": [],
      "rarity": ""
    },
    {
      "id": "sv03.5-088",
      "name": "Grimer",
      "searchName": "Grimer",
      "collectionId": "sv03.5",
      "collectionName": "151",
      "ligaSetCode": "MEW",
      "tcgdexSetId": "sv03.5",
      "number": "088",
      "printedTotal": "165",
      "imageUrl": "https://assets.tcgdex.net/pt/sv/sv03.5/088",
      "types": [],
      "rarity": ""
    },
    {
      "id": "sv03.5-089",
      "name": "Muk",
      "searchName": "Muk",
      "collectionId": "sv03.5",
      "collectionName": "151",
      "ligaSetCode": "MEW",
      "tcgdexSetId": "sv03.5",
      "number": "089",
      "printedTotal": "165",
      "imageUrl": "https://assets.tcgdex.net/pt/sv/sv03.5/089",
      "types": [],
      "rarity": ""
    },
    {
      "id": "sv03.5-090",
      "name": "Shellder",
      "searchName": "Shellder",
      "collectionId": "sv03.5",
      "collectionName": "151",
      "ligaSetCode": "MEW",
      "tcgdexSetId": "sv03.5",
      "number": "090",
      "printedTotal": "165",
      "imageUrl": "https://assets.tcgdex.net/pt/sv/sv03.5/090",
      "types": [],
      "rarity": ""
    },
    {
      "id": "sv03.5-091",
      "name": "Cloyster",
      "searchName": "Cloyster",
      "collectionId": "sv03.5",
      "collectionName": "151",
      "ligaSetCode": "MEW",
      "tcgdexSetId": "sv03.5",
      "number": "091",
      "printedTotal": "165",
      "imageUrl": "https://assets.tcgdex.net/pt/sv/sv03.5/091",
      "types": [],
      "rarity": ""
    },
    {
      "id": "sv03.5-092",
      "name": "Gastly",
      "searchName": "Gastly",
      "collectionId": "sv03.5",
      "collectionName": "151",
      "ligaSetCode": "MEW",
      "tcgdexSetId": "sv03.5",
      "number": "092",
      "printedTotal": "165",
      "imageUrl": "https://assets.tcgdex.net/pt/sv/sv03.5/092",
      "types": [],
      "rarity": ""
    },
    {
      "id": "sv03.5-093",
      "name": "Haunter",
      "searchName": "Haunter",
      "collectionId": "sv03.5",
      "collectionName": "151",
      "ligaSetCode": "MEW",
      "tcgdexSetId": "sv03.5",
      "number": "093",
      "printedTotal": "165",
      "imageUrl": "https://assets.tcgdex.net/pt/sv/sv03.5/093",
      "types": [],
      "rarity": ""
    },
    {
      "id": "sv03.5-094",
      "name": "Gengar",
      "searchName": "Gengar",
      "collectionId": "sv03.5",
      "collectionName": "151",
      "ligaSetCode": "MEW",
      "tcgdexSetId": "sv03.5",
      "number": "094",
      "printedTotal": "165",
      "imageUrl": "https://assets.tcgdex.net/pt/sv/sv03.5/094",
      "types": [],
      "rarity": ""
    },
    {
      "id": "sv03.5-095",
      "name": "Onix",
      "searchName": "Onix",
      "collectionId": "sv03.5",
      "collectionName": "151",
      "ligaSetCode": "MEW",
      "tcgdexSetId": "sv03.5",
      "number": "095",
      "printedTotal": "165",
      "imageUrl": "https://assets.tcgdex.net/pt/sv/sv03.5/095",
      "types": [],
      "rarity": ""
    },
    {
      "id": "sv03.5-096",
      "name": "Drowzee",
      "searchName": "Drowzee",
      "collectionId": "sv03.5",
      "collectionName": "151",
      "ligaSetCode": "MEW",
      "tcgdexSetId": "sv03.5",
      "number": "096",
      "printedTotal": "165",
      "imageUrl": "https://assets.tcgdex.net/pt/sv/sv03.5/096",
      "types": [],
      "rarity": ""
    },
    {
      "id": "sv03.5-097",
      "name": "Hypno",
      "searchName": "Hypno",
      "collectionId": "sv03.5",
      "collectionName": "151",
      "ligaSetCode": "MEW",
      "tcgdexSetId": "sv03.5",
      "number": "097",
      "printedTotal": "165",
      "imageUrl": "https://assets.tcgdex.net/pt/sv/sv03.5/097",
      "types": [],
      "rarity": ""
    },
    {
      "id": "sv03.5-098",
      "name": "Krabby",
      "searchName": "Krabby",
      "collectionId": "sv03.5",
      "collectionName": "151",
      "ligaSetCode": "MEW",
      "tcgdexSetId": "sv03.5",
      "number": "098",
      "printedTotal": "165",
      "imageUrl": "https://assets.tcgdex.net/pt/sv/sv03.5/098",
      "types": [],
      "rarity": ""
    },
    {
      "id": "sv03.5-099",
      "name": "Kingler",
      "searchName": "Kingler",
      "collectionId": "sv03.5",
      "collectionName": "151",
      "ligaSetCode": "MEW",
      "tcgdexSetId": "sv03.5",
      "number": "099",
      "printedTotal": "165",
      "imageUrl": "https://assets.tcgdex.net/pt/sv/sv03.5/099",
      "types": [],
      "rarity": ""
    },
    {
      "id": "sv03.5-100",
      "name": "Voltorb",
      "searchName": "Voltorb",
      "collectionId": "sv03.5",
      "collectionName": "151",
      "ligaSetCode": "MEW",
      "tcgdexSetId": "sv03.5",
      "number": "100",
      "printedTotal": "165",
      "imageUrl": "https://assets.tcgdex.net/pt/sv/sv03.5/100",
      "types": [],
      "rarity": ""
    },
    {
      "id": "sv03.5-101",
      "name": "Electrode",
      "searchName": "Electrode",
      "collectionId": "sv03.5",
      "collectionName": "151",
      "ligaSetCode": "MEW",
      "tcgdexSetId": "sv03.5",
      "number": "101",
      "printedTotal": "165",
      "imageUrl": "https://assets.tcgdex.net/pt/sv/sv03.5/101",
      "types": [],
      "rarity": ""
    },
    {
      "id": "sv03.5-102",
      "name": "Exeggcute",
      "searchName": "Exeggcute",
      "collectionId": "sv03.5",
      "collectionName": "151",
      "ligaSetCode": "MEW",
      "tcgdexSetId": "sv03.5",
      "number": "102",
      "printedTotal": "165",
      "imageUrl": "https://assets.tcgdex.net/pt/sv/sv03.5/102",
      "types": [],
      "rarity": ""
    },
    {
      "id": "sv03.5-103",
      "name": "Exeggutor",
      "searchName": "Exeggutor",
      "collectionId": "sv03.5",
      "collectionName": "151",
      "ligaSetCode": "MEW",
      "tcgdexSetId": "sv03.5",
      "number": "103",
      "printedTotal": "165",
      "imageUrl": "https://assets.tcgdex.net/pt/sv/sv03.5/103",
      "types": [],
      "rarity": ""
    },
    {
      "id": "sv03.5-104",
      "name": "Cubone",
      "searchName": "Cubone",
      "collectionId": "sv03.5",
      "collectionName": "151",
      "ligaSetCode": "MEW",
      "tcgdexSetId": "sv03.5",
      "number": "104",
      "printedTotal": "165",
      "imageUrl": "https://assets.tcgdex.net/pt/sv/sv03.5/104",
      "types": [],
      "rarity": ""
    },
    {
      "id": "sv03.5-105",
      "name": "Marowak",
      "searchName": "Marowak",
      "collectionId": "sv03.5",
      "collectionName": "151",
      "ligaSetCode": "MEW",
      "tcgdexSetId": "sv03.5",
      "number": "105",
      "printedTotal": "165",
      "imageUrl": "https://assets.tcgdex.net/pt/sv/sv03.5/105",
      "types": [],
      "rarity": ""
    },
    {
      "id": "sv03.5-106",
      "name": "Hitmonlee",
      "searchName": "Hitmonlee",
      "collectionId": "sv03.5",
      "collectionName": "151",
      "ligaSetCode": "MEW",
      "tcgdexSetId": "sv03.5",
      "number": "106",
      "printedTotal": "165",
      "imageUrl": "https://assets.tcgdex.net/pt/sv/sv03.5/106",
      "types": [],
      "rarity": ""
    },
    {
      "id": "sv03.5-107",
      "name": "Hitmonchan",
      "searchName": "Hitmonchan",
      "collectionId": "sv03.5",
      "collectionName": "151",
      "ligaSetCode": "MEW",
      "tcgdexSetId": "sv03.5",
      "number": "107",
      "printedTotal": "165",
      "imageUrl": "https://assets.tcgdex.net/pt/sv/sv03.5/107",
      "types": [],
      "rarity": ""
    },
    {
      "id": "sv03.5-108",
      "name": "Lickitung",
      "searchName": "Lickitung",
      "collectionId": "sv03.5",
      "collectionName": "151",
      "ligaSetCode": "MEW",
      "tcgdexSetId": "sv03.5",
      "number": "108",
      "printedTotal": "165",
      "imageUrl": "https://assets.tcgdex.net/pt/sv/sv03.5/108",
      "types": [],
      "rarity": ""
    },
    {
      "id": "sv03.5-109",
      "name": "Koffing",
      "searchName": "Koffing",
      "collectionId": "sv03.5",
      "collectionName": "151",
      "ligaSetCode": "MEW",
      "tcgdexSetId": "sv03.5",
      "number": "109",
      "printedTotal": "165",
      "imageUrl": "https://assets.tcgdex.net/pt/sv/sv03.5/109",
      "types": [],
      "rarity": ""
    },
    {
      "id": "sv03.5-110",
      "name": "Weezing",
      "searchName": "Weezing",
      "collectionId": "sv03.5",
      "collectionName": "151",
      "ligaSetCode": "MEW",
      "tcgdexSetId": "sv03.5",
      "number": "110",
      "printedTotal": "165",
      "imageUrl": "https://assets.tcgdex.net/pt/sv/sv03.5/110",
      "types": [],
      "rarity": ""
    },
    {
      "id": "sv03.5-111",
      "name": "Rhyhorn",
      "searchName": "Rhyhorn",
      "collectionId": "sv03.5",
      "collectionName": "151",
      "ligaSetCode": "MEW",
      "tcgdexSetId": "sv03.5",
      "number": "111",
      "printedTotal": "165",
      "imageUrl": "https://assets.tcgdex.net/pt/sv/sv03.5/111",
      "types": [],
      "rarity": ""
    },
    {
      "id": "sv03.5-112",
      "name": "Rhydon",
      "searchName": "Rhydon",
      "collectionId": "sv03.5",
      "collectionName": "151",
      "ligaSetCode": "MEW",
      "tcgdexSetId": "sv03.5",
      "number": "112",
      "printedTotal": "165",
      "imageUrl": "https://assets.tcgdex.net/pt/sv/sv03.5/112",
      "types": [],
      "rarity": ""
    },
    {
      "id": "sv03.5-113",
      "name": "Chansey",
      "searchName": "Chansey",
      "collectionId": "sv03.5",
      "collectionName": "151",
      "ligaSetCode": "MEW",
      "tcgdexSetId": "sv03.5",
      "number": "113",
      "printedTotal": "165",
      "imageUrl": "https://assets.tcgdex.net/pt/sv/sv03.5/113",
      "types": [],
      "rarity": ""
    },
    {
      "id": "sv03.5-114",
      "name": "Tangela",
      "searchName": "Tangela",
      "collectionId": "sv03.5",
      "collectionName": "151",
      "ligaSetCode": "MEW",
      "tcgdexSetId": "sv03.5",
      "number": "114",
      "printedTotal": "165",
      "imageUrl": "https://assets.tcgdex.net/pt/sv/sv03.5/114",
      "types": [],
      "rarity": ""
    },
    {
      "id": "sv03.5-115",
      "name": "Kangaskhan ex",
      "searchName": "Kangaskhan ex",
      "collectionId": "sv03.5",
      "collectionName": "151",
      "ligaSetCode": "MEW",
      "tcgdexSetId": "sv03.5",
      "number": "115",
      "printedTotal": "165",
      "imageUrl": "https://assets.tcgdex.net/pt/sv/sv03.5/115",
      "types": [],
      "rarity": ""
    },
    {
      "id": "sv03.5-116",
      "name": "Horsea",
      "searchName": "Horsea",
      "collectionId": "sv03.5",
      "collectionName": "151",
      "ligaSetCode": "MEW",
      "tcgdexSetId": "sv03.5",
      "number": "116",
      "printedTotal": "165",
      "imageUrl": "https://assets.tcgdex.net/pt/sv/sv03.5/116",
      "types": [],
      "rarity": ""
    },
    {
      "id": "sv03.5-117",
      "name": "Seadra",
      "searchName": "Seadra",
      "collectionId": "sv03.5",
      "collectionName": "151",
      "ligaSetCode": "MEW",
      "tcgdexSetId": "sv03.5",
      "number": "117",
      "printedTotal": "165",
      "imageUrl": "https://assets.tcgdex.net/pt/sv/sv03.5/117",
      "types": [],
      "rarity": ""
    },
    {
      "id": "sv03.5-118",
      "name": "Goldeen",
      "searchName": "Goldeen",
      "collectionId": "sv03.5",
      "collectionName": "151",
      "ligaSetCode": "MEW",
      "tcgdexSetId": "sv03.5",
      "number": "118",
      "printedTotal": "165",
      "imageUrl": "https://assets.tcgdex.net/pt/sv/sv03.5/118",
      "types": [],
      "rarity": ""
    },
    {
      "id": "sv03.5-119",
      "name": "Seaking",
      "searchName": "Seaking",
      "collectionId": "sv03.5",
      "collectionName": "151",
      "ligaSetCode": "MEW",
      "tcgdexSetId": "sv03.5",
      "number": "119",
      "printedTotal": "165",
      "imageUrl": "https://assets.tcgdex.net/pt/sv/sv03.5/119",
      "types": [],
      "rarity": ""
    },
    {
      "id": "sv03.5-120",
      "name": "Staryu",
      "searchName": "Staryu",
      "collectionId": "sv03.5",
      "collectionName": "151",
      "ligaSetCode": "MEW",
      "tcgdexSetId": "sv03.5",
      "number": "120",
      "printedTotal": "165",
      "imageUrl": "https://assets.tcgdex.net/pt/sv/sv03.5/120",
      "types": [],
      "rarity": ""
    },
    {
      "id": "sv03.5-121",
      "name": "Starmie",
      "searchName": "Starmie",
      "collectionId": "sv03.5",
      "collectionName": "151",
      "ligaSetCode": "MEW",
      "tcgdexSetId": "sv03.5",
      "number": "121",
      "printedTotal": "165",
      "imageUrl": "https://assets.tcgdex.net/pt/sv/sv03.5/121",
      "types": [],
      "rarity": ""
    },
    {
      "id": "sv03.5-122",
      "name": "Mr. Mime",
      "searchName": "Mr. Mime",
      "collectionId": "sv03.5",
      "collectionName": "151",
      "ligaSetCode": "MEW",
      "tcgdexSetId": "sv03.5",
      "number": "122",
      "printedTotal": "165",
      "imageUrl": "https://assets.tcgdex.net/pt/sv/sv03.5/122",
      "types": [],
      "rarity": ""
    },
    {
      "id": "sv03.5-123",
      "name": "Scyther",
      "searchName": "Scyther",
      "collectionId": "sv03.5",
      "collectionName": "151",
      "ligaSetCode": "MEW",
      "tcgdexSetId": "sv03.5",
      "number": "123",
      "printedTotal": "165",
      "imageUrl": "https://assets.tcgdex.net/pt/sv/sv03.5/123",
      "types": [],
      "rarity": ""
    },
    {
      "id": "sv03.5-124",
      "name": "Jynx ex",
      "searchName": "Jynx ex",
      "collectionId": "sv03.5",
      "collectionName": "151",
      "ligaSetCode": "MEW",
      "tcgdexSetId": "sv03.5",
      "number": "124",
      "printedTotal": "165",
      "imageUrl": "https://assets.tcgdex.net/pt/sv/sv03.5/124",
      "types": [],
      "rarity": ""
    },
    {
      "id": "sv03.5-125",
      "name": "Electabuzz",
      "searchName": "Electabuzz",
      "collectionId": "sv03.5",
      "collectionName": "151",
      "ligaSetCode": "MEW",
      "tcgdexSetId": "sv03.5",
      "number": "125",
      "printedTotal": "165",
      "imageUrl": "https://assets.tcgdex.net/pt/sv/sv03.5/125",
      "types": [],
      "rarity": ""
    },
    {
      "id": "sv03.5-126",
      "name": "Magmar",
      "searchName": "Magmar",
      "collectionId": "sv03.5",
      "collectionName": "151",
      "ligaSetCode": "MEW",
      "tcgdexSetId": "sv03.5",
      "number": "126",
      "printedTotal": "165",
      "imageUrl": "https://assets.tcgdex.net/pt/sv/sv03.5/126",
      "types": [],
      "rarity": ""
    },
    {
      "id": "sv03.5-127",
      "name": "Pinsir",
      "searchName": "Pinsir",
      "collectionId": "sv03.5",
      "collectionName": "151",
      "ligaSetCode": "MEW",
      "tcgdexSetId": "sv03.5",
      "number": "127",
      "printedTotal": "165",
      "imageUrl": "https://assets.tcgdex.net/pt/sv/sv03.5/127",
      "types": [],
      "rarity": ""
    },
    {
      "id": "sv03.5-128",
      "name": "Tauros",
      "searchName": "Tauros",
      "collectionId": "sv03.5",
      "collectionName": "151",
      "ligaSetCode": "MEW",
      "tcgdexSetId": "sv03.5",
      "number": "128",
      "printedTotal": "165",
      "imageUrl": "https://assets.tcgdex.net/pt/sv/sv03.5/128",
      "types": [],
      "rarity": ""
    },
    {
      "id": "sv03.5-129",
      "name": "Magikarp",
      "searchName": "Magikarp",
      "collectionId": "sv03.5",
      "collectionName": "151",
      "ligaSetCode": "MEW",
      "tcgdexSetId": "sv03.5",
      "number": "129",
      "printedTotal": "165",
      "imageUrl": "https://assets.tcgdex.net/pt/sv/sv03.5/129",
      "types": [],
      "rarity": ""
    },
    {
      "id": "sv03.5-130",
      "name": "Gyarados",
      "searchName": "Gyarados",
      "collectionId": "sv03.5",
      "collectionName": "151",
      "ligaSetCode": "MEW",
      "tcgdexSetId": "sv03.5",
      "number": "130",
      "printedTotal": "165",
      "imageUrl": "https://assets.tcgdex.net/pt/sv/sv03.5/130",
      "types": [],
      "rarity": ""
    },
    {
      "id": "sv03.5-131",
      "name": "Lapras",
      "searchName": "Lapras",
      "collectionId": "sv03.5",
      "collectionName": "151",
      "ligaSetCode": "MEW",
      "tcgdexSetId": "sv03.5",
      "number": "131",
      "printedTotal": "165",
      "imageUrl": "https://assets.tcgdex.net/pt/sv/sv03.5/131",
      "types": [],
      "rarity": ""
    },
    {
      "id": "sv03.5-132",
      "name": "Ditto",
      "searchName": "Ditto",
      "collectionId": "sv03.5",
      "collectionName": "151",
      "ligaSetCode": "MEW",
      "tcgdexSetId": "sv03.5",
      "number": "132",
      "printedTotal": "165",
      "imageUrl": "https://assets.tcgdex.net/pt/sv/sv03.5/132",
      "types": [],
      "rarity": ""
    },
    {
      "id": "sv03.5-133",
      "name": "Eevee",
      "searchName": "Eevee",
      "collectionId": "sv03.5",
      "collectionName": "151",
      "ligaSetCode": "MEW",
      "tcgdexSetId": "sv03.5",
      "number": "133",
      "printedTotal": "165",
      "imageUrl": "https://assets.tcgdex.net/pt/sv/sv03.5/133",
      "types": [],
      "rarity": ""
    },
    {
      "id": "sv03.5-134",
      "name": "Vaporeon",
      "searchName": "Vaporeon",
      "collectionId": "sv03.5",
      "collectionName": "151",
      "ligaSetCode": "MEW",
      "tcgdexSetId": "sv03.5",
      "number": "134",
      "printedTotal": "165",
      "imageUrl": "https://assets.tcgdex.net/pt/sv/sv03.5/134",
      "types": [],
      "rarity": ""
    },
    {
      "id": "sv03.5-135",
      "name": "Jolteon",
      "searchName": "Jolteon",
      "collectionId": "sv03.5",
      "collectionName": "151",
      "ligaSetCode": "MEW",
      "tcgdexSetId": "sv03.5",
      "number": "135",
      "printedTotal": "165",
      "imageUrl": "https://assets.tcgdex.net/pt/sv/sv03.5/135",
      "types": [],
      "rarity": ""
    },
    {
      "id": "sv03.5-136",
      "name": "Flareon",
      "searchName": "Flareon",
      "collectionId": "sv03.5",
      "collectionName": "151",
      "ligaSetCode": "MEW",
      "tcgdexSetId": "sv03.5",
      "number": "136",
      "printedTotal": "165",
      "imageUrl": "https://assets.tcgdex.net/pt/sv/sv03.5/136",
      "types": [],
      "rarity": ""
    },
    {
      "id": "sv03.5-137",
      "name": "Porygon",
      "searchName": "Porygon",
      "collectionId": "sv03.5",
      "collectionName": "151",
      "ligaSetCode": "MEW",
      "tcgdexSetId": "sv03.5",
      "number": "137",
      "printedTotal": "165",
      "imageUrl": "https://assets.tcgdex.net/pt/sv/sv03.5/137",
      "types": [],
      "rarity": ""
    },
    {
      "id": "sv03.5-138",
      "name": "Omanyte",
      "searchName": "Omanyte",
      "collectionId": "sv03.5",
      "collectionName": "151",
      "ligaSetCode": "MEW",
      "tcgdexSetId": "sv03.5",
      "number": "138",
      "printedTotal": "165",
      "imageUrl": "https://assets.tcgdex.net/pt/sv/sv03.5/138",
      "types": [],
      "rarity": ""
    },
    {
      "id": "sv03.5-139",
      "name": "Omastar",
      "searchName": "Omastar",
      "collectionId": "sv03.5",
      "collectionName": "151",
      "ligaSetCode": "MEW",
      "tcgdexSetId": "sv03.5",
      "number": "139",
      "printedTotal": "165",
      "imageUrl": "https://assets.tcgdex.net/pt/sv/sv03.5/139",
      "types": [],
      "rarity": ""
    },
    {
      "id": "sv03.5-140",
      "name": "Kabuto",
      "searchName": "Kabuto",
      "collectionId": "sv03.5",
      "collectionName": "151",
      "ligaSetCode": "MEW",
      "tcgdexSetId": "sv03.5",
      "number": "140",
      "printedTotal": "165",
      "imageUrl": "https://assets.tcgdex.net/pt/sv/sv03.5/140",
      "types": [],
      "rarity": ""
    },
    {
      "id": "sv03.5-141",
      "name": "Kabutops",
      "searchName": "Kabutops",
      "collectionId": "sv03.5",
      "collectionName": "151",
      "ligaSetCode": "MEW",
      "tcgdexSetId": "sv03.5",
      "number": "141",
      "printedTotal": "165",
      "imageUrl": "https://assets.tcgdex.net/pt/sv/sv03.5/141",
      "types": [],
      "rarity": ""
    },
    {
      "id": "sv03.5-142",
      "name": "Aerodactyl",
      "searchName": "Aerodactyl",
      "collectionId": "sv03.5",
      "collectionName": "151",
      "ligaSetCode": "MEW",
      "tcgdexSetId": "sv03.5",
      "number": "142",
      "printedTotal": "165",
      "imageUrl": "https://assets.tcgdex.net/pt/sv/sv03.5/142",
      "types": [],
      "rarity": ""
    },
    {
      "id": "sv03.5-143",
      "name": "Snorlax",
      "searchName": "Snorlax",
      "collectionId": "sv03.5",
      "collectionName": "151",
      "ligaSetCode": "MEW",
      "tcgdexSetId": "sv03.5",
      "number": "143",
      "printedTotal": "165",
      "imageUrl": "https://assets.tcgdex.net/pt/sv/sv03.5/143",
      "types": [],
      "rarity": ""
    },
    {
      "id": "sv03.5-144",
      "name": "Articuno",
      "searchName": "Articuno",
      "collectionId": "sv03.5",
      "collectionName": "151",
      "ligaSetCode": "MEW",
      "tcgdexSetId": "sv03.5",
      "number": "144",
      "printedTotal": "165",
      "imageUrl": "https://assets.tcgdex.net/pt/sv/sv03.5/144",
      "types": [],
      "rarity": ""
    },
    {
      "id": "sv03.5-145",
      "name": "Zapdos ex",
      "searchName": "Zapdos ex",
      "collectionId": "sv03.5",
      "collectionName": "151",
      "ligaSetCode": "MEW",
      "tcgdexSetId": "sv03.5",
      "number": "145",
      "printedTotal": "165",
      "imageUrl": "https://assets.tcgdex.net/pt/sv/sv03.5/145",
      "types": [],
      "rarity": ""
    },
    {
      "id": "sv03.5-146",
      "name": "Moltres",
      "searchName": "Moltres",
      "collectionId": "sv03.5",
      "collectionName": "151",
      "ligaSetCode": "MEW",
      "tcgdexSetId": "sv03.5",
      "number": "146",
      "printedTotal": "165",
      "imageUrl": "https://assets.tcgdex.net/pt/sv/sv03.5/146",
      "types": [],
      "rarity": ""
    },
    {
      "id": "sv03.5-147",
      "name": "Dratini",
      "searchName": "Dratini",
      "collectionId": "sv03.5",
      "collectionName": "151",
      "ligaSetCode": "MEW",
      "tcgdexSetId": "sv03.5",
      "number": "147",
      "printedTotal": "165",
      "imageUrl": "https://assets.tcgdex.net/pt/sv/sv03.5/147",
      "types": [],
      "rarity": ""
    },
    {
      "id": "sv03.5-148",
      "name": "Dragonair",
      "searchName": "Dragonair",
      "collectionId": "sv03.5",
      "collectionName": "151",
      "ligaSetCode": "MEW",
      "tcgdexSetId": "sv03.5",
      "number": "148",
      "printedTotal": "165",
      "imageUrl": "https://assets.tcgdex.net/pt/sv/sv03.5/148",
      "types": [],
      "rarity": ""
    },
    {
      "id": "sv03.5-149",
      "name": "Dragonite",
      "searchName": "Dragonite",
      "collectionId": "sv03.5",
      "collectionName": "151",
      "ligaSetCode": "MEW",
      "tcgdexSetId": "sv03.5",
      "number": "149",
      "printedTotal": "165",
      "imageUrl": "https://assets.tcgdex.net/pt/sv/sv03.5/149",
      "types": [],
      "rarity": ""
    },
    {
      "id": "sv03.5-150",
      "name": "Mewtwo",
      "searchName": "Mewtwo",
      "collectionId": "sv03.5",
      "collectionName": "151",
      "ligaSetCode": "MEW",
      "tcgdexSetId": "sv03.5",
      "number": "150",
      "printedTotal": "165",
      "imageUrl": "https://assets.tcgdex.net/pt/sv/sv03.5/150",
      "types": [],
      "rarity": ""
    },
    {
      "id": "sv03.5-151",
      "name": "Mew ex",
      "searchName": "Mew ex",
      "collectionId": "sv03.5",
      "collectionName": "151",
      "ligaSetCode": "MEW",
      "tcgdexSetId": "sv03.5",
      "number": "151",
      "printedTotal": "165",
      "imageUrl": "https://assets.tcgdex.net/pt/sv/sv03.5/151",
      "types": [],
      "rarity": ""
    },
    {
      "id": "sv03.5-152",
      "name": "Fóssil Cúpula Arcaico",
      "searchName": "Fóssil Cúpula Arcaico",
      "collectionId": "sv03.5",
      "collectionName": "151",
      "ligaSetCode": "MEW",
      "tcgdexSetId": "sv03.5",
      "number": "152",
      "printedTotal": "165",
      "imageUrl": "https://assets.tcgdex.net/pt/sv/sv03.5/152",
      "types": [],
      "rarity": ""
    },
    {
      "id": "sv03.5-153",
      "name": "Fóssil Espiral Arcaico",
      "searchName": "Fóssil Espiral Arcaico",
      "collectionId": "sv03.5",
      "collectionName": "151",
      "ligaSetCode": "MEW",
      "tcgdexSetId": "sv03.5",
      "number": "153",
      "printedTotal": "165",
      "imageUrl": "https://assets.tcgdex.net/pt/sv/sv03.5/153",
      "types": [],
      "rarity": ""
    },
    {
      "id": "sv03.5-154",
      "name": "Âmbar Velho Arcaico",
      "searchName": "Âmbar Velho Arcaico",
      "collectionId": "sv03.5",
      "collectionName": "151",
      "ligaSetCode": "MEW",
      "tcgdexSetId": "sv03.5",
      "number": "154",
      "printedTotal": "165",
      "imageUrl": "https://assets.tcgdex.net/pt/sv/sv03.5/154",
      "types": [],
      "rarity": ""
    },
    {
      "id": "sv03.5-155",
      "name": "Grande Balão de Ar",
      "searchName": "Grande Balão de Ar",
      "collectionId": "sv03.5",
      "collectionName": "151",
      "ligaSetCode": "MEW",
      "tcgdexSetId": "sv03.5",
      "number": "155",
      "printedTotal": "165",
      "imageUrl": "https://assets.tcgdex.net/pt/sv/sv03.5/155",
      "types": [],
      "rarity": ""
    },
    {
      "id": "sv03.5-156",
      "name": "Transferência do Bill",
      "searchName": "Transferência do Bill",
      "collectionId": "sv03.5",
      "collectionName": "151",
      "ligaSetCode": "MEW",
      "tcgdexSetId": "sv03.5",
      "number": "156",
      "printedTotal": "165",
      "imageUrl": "https://assets.tcgdex.net/pt/sv/sv03.5/156",
      "types": [],
      "rarity": ""
    },
    {
      "id": "sv03.5-157",
      "name": "Ciclovia",
      "searchName": "Ciclovia",
      "collectionId": "sv03.5",
      "collectionName": "151",
      "ligaSetCode": "MEW",
      "tcgdexSetId": "sv03.5",
      "number": "157",
      "printedTotal": "165",
      "imageUrl": "https://assets.tcgdex.net/pt/sv/sv03.5/157",
      "types": [],
      "rarity": ""
    },
    {
      "id": "sv03.5-158",
      "name": "Ajuda da Daisy",
      "searchName": "Ajuda da Daisy",
      "collectionId": "sv03.5",
      "collectionName": "151",
      "ligaSetCode": "MEW",
      "tcgdexSetId": "sv03.5",
      "number": "158",
      "printedTotal": "165",
      "imageUrl": "https://assets.tcgdex.net/pt/sv/sv03.5/158",
      "types": [],
      "rarity": ""
    },
    {
      "id": "sv03.5-159",
      "name": "Adesivo de Energia",
      "searchName": "Adesivo de Energia",
      "collectionId": "sv03.5",
      "collectionName": "151",
      "ligaSetCode": "MEW",
      "tcgdexSetId": "sv03.5",
      "number": "159",
      "printedTotal": "165",
      "imageUrl": "https://assets.tcgdex.net/pt/sv/sv03.5/159",
      "types": [],
      "rarity": ""
    },
    {
      "id": "sv03.5-160",
      "name": "Convite da Érica",
      "searchName": "Convite da Érica",
      "collectionId": "sv03.5",
      "collectionName": "151",
      "ligaSetCode": "MEW",
      "tcgdexSetId": "sv03.5",
      "number": "160",
      "printedTotal": "165",
      "imageUrl": "https://assets.tcgdex.net/pt/sv/sv03.5/160",
      "types": [],
      "rarity": ""
    },
    {
      "id": "sv03.5-161",
      "name": "Carisma do Giovanni",
      "searchName": "Carisma do Giovanni",
      "collectionId": "sv03.5",
      "collectionName": "151",
      "ligaSetCode": "MEW",
      "tcgdexSetId": "sv03.5",
      "number": "161",
      "printedTotal": "165",
      "imageUrl": "https://assets.tcgdex.net/pt/sv/sv03.5/161",
      "types": [],
      "rarity": ""
    },
    {
      "id": "sv03.5-162",
      "name": "Apanhador",
      "searchName": "Apanhador",
      "collectionId": "sv03.5",
      "collectionName": "151",
      "ligaSetCode": "MEW",
      "tcgdexSetId": "sv03.5",
      "number": "162",
      "printedTotal": "165",
      "imageUrl": "https://assets.tcgdex.net/pt/sv/sv03.5/162",
      "types": [],
      "rarity": ""
    },
    {
      "id": "sv03.5-163",
      "name": "Sobras",
      "searchName": "Sobras",
      "collectionId": "sv03.5",
      "collectionName": "151",
      "ligaSetCode": "MEW",
      "tcgdexSetId": "sv03.5",
      "number": "163",
      "printedTotal": "165",
      "imageUrl": "https://assets.tcgdex.net/pt/sv/sv03.5/163",
      "types": [],
      "rarity": ""
    },
    {
      "id": "sv03.5-164",
      "name": "Óculos Protetores",
      "searchName": "Óculos Protetores",
      "collectionId": "sv03.5",
      "collectionName": "151",
      "ligaSetCode": "MEW",
      "tcgdexSetId": "sv03.5",
      "number": "164",
      "printedTotal": "165",
      "imageUrl": "https://assets.tcgdex.net/pt/sv/sv03.5/164",
      "types": [],
      "rarity": ""
    },
    {
      "id": "sv03.5-165",
      "name": "Faixa da Rigidez",
      "searchName": "Faixa da Rigidez",
      "collectionId": "sv03.5",
      "collectionName": "151",
      "ligaSetCode": "MEW",
      "tcgdexSetId": "sv03.5",
      "number": "165",
      "printedTotal": "165",
      "imageUrl": "https://assets.tcgdex.net/pt/sv/sv03.5/165",
      "types": [],
      "rarity": ""
    },
    {
      "id": "sv03.5-166",
      "name": "Bulbasaur",
      "searchName": "Bulbasaur",
      "collectionId": "sv03.5",
      "collectionName": "151",
      "ligaSetCode": "MEW",
      "tcgdexSetId": "sv03.5",
      "number": "166",
      "printedTotal": "165",
      "imageUrl": "https://assets.tcgdex.net/pt/sv/sv03.5/166",
      "types": [],
      "rarity": ""
    },
    {
      "id": "sv03.5-167",
      "name": "Ivysaur",
      "searchName": "Ivysaur",
      "collectionId": "sv03.5",
      "collectionName": "151",
      "ligaSetCode": "MEW",
      "tcgdexSetId": "sv03.5",
      "number": "167",
      "printedTotal": "165",
      "imageUrl": "https://assets.tcgdex.net/pt/sv/sv03.5/167",
      "types": [],
      "rarity": ""
    },
    {
      "id": "sv03.5-168",
      "name": "Charmander",
      "searchName": "Charmander",
      "collectionId": "sv03.5",
      "collectionName": "151",
      "ligaSetCode": "MEW",
      "tcgdexSetId": "sv03.5",
      "number": "168",
      "printedTotal": "165",
      "imageUrl": "https://assets.tcgdex.net/pt/sv/sv03.5/168",
      "types": [],
      "rarity": ""
    },
    {
      "id": "sv03.5-169",
      "name": "Charmeleon",
      "searchName": "Charmeleon",
      "collectionId": "sv03.5",
      "collectionName": "151",
      "ligaSetCode": "MEW",
      "tcgdexSetId": "sv03.5",
      "number": "169",
      "printedTotal": "165",
      "imageUrl": "https://assets.tcgdex.net/pt/sv/sv03.5/169",
      "types": [],
      "rarity": ""
    },
    {
      "id": "sv03.5-170",
      "name": "Squirtle",
      "searchName": "Squirtle",
      "collectionId": "sv03.5",
      "collectionName": "151",
      "ligaSetCode": "MEW",
      "tcgdexSetId": "sv03.5",
      "number": "170",
      "printedTotal": "165",
      "imageUrl": "https://assets.tcgdex.net/pt/sv/sv03.5/170",
      "types": [],
      "rarity": ""
    },
    {
      "id": "sv03.5-171",
      "name": "Wartortle",
      "searchName": "Wartortle",
      "collectionId": "sv03.5",
      "collectionName": "151",
      "ligaSetCode": "MEW",
      "tcgdexSetId": "sv03.5",
      "number": "171",
      "printedTotal": "165",
      "imageUrl": "https://assets.tcgdex.net/pt/sv/sv03.5/171",
      "types": [],
      "rarity": ""
    },
    {
      "id": "sv03.5-172",
      "name": "Caterpie",
      "searchName": "Caterpie",
      "collectionId": "sv03.5",
      "collectionName": "151",
      "ligaSetCode": "MEW",
      "tcgdexSetId": "sv03.5",
      "number": "172",
      "printedTotal": "165",
      "imageUrl": "https://assets.tcgdex.net/pt/sv/sv03.5/172",
      "types": [],
      "rarity": ""
    },
    {
      "id": "sv03.5-173",
      "name": "Pikachu",
      "searchName": "Pikachu",
      "collectionId": "sv03.5",
      "collectionName": "151",
      "ligaSetCode": "MEW",
      "tcgdexSetId": "sv03.5",
      "number": "173",
      "printedTotal": "165",
      "imageUrl": "https://assets.tcgdex.net/pt/sv/sv03.5/173",
      "types": [],
      "rarity": ""
    },
    {
      "id": "sv03.5-174",
      "name": "Nidoking",
      "searchName": "Nidoking",
      "collectionId": "sv03.5",
      "collectionName": "151",
      "ligaSetCode": "MEW",
      "tcgdexSetId": "sv03.5",
      "number": "174",
      "printedTotal": "165",
      "imageUrl": "https://assets.tcgdex.net/pt/sv/sv03.5/174",
      "types": [],
      "rarity": ""
    },
    {
      "id": "sv03.5-175",
      "name": "Psyduck",
      "searchName": "Psyduck",
      "collectionId": "sv03.5",
      "collectionName": "151",
      "ligaSetCode": "MEW",
      "tcgdexSetId": "sv03.5",
      "number": "175",
      "printedTotal": "165",
      "imageUrl": "https://assets.tcgdex.net/pt/sv/sv03.5/175",
      "types": [],
      "rarity": ""
    },
    {
      "id": "sv03.5-176",
      "name": "Poliwhirl",
      "searchName": "Poliwhirl",
      "collectionId": "sv03.5",
      "collectionName": "151",
      "ligaSetCode": "MEW",
      "tcgdexSetId": "sv03.5",
      "number": "176",
      "printedTotal": "165",
      "imageUrl": "https://assets.tcgdex.net/pt/sv/sv03.5/176",
      "types": [],
      "rarity": ""
    },
    {
      "id": "sv03.5-177",
      "name": "Machoke",
      "searchName": "Machoke",
      "collectionId": "sv03.5",
      "collectionName": "151",
      "ligaSetCode": "MEW",
      "tcgdexSetId": "sv03.5",
      "number": "177",
      "printedTotal": "165",
      "imageUrl": "https://assets.tcgdex.net/pt/sv/sv03.5/177",
      "types": [],
      "rarity": ""
    },
    {
      "id": "sv03.5-178",
      "name": "Tangela",
      "searchName": "Tangela",
      "collectionId": "sv03.5",
      "collectionName": "151",
      "ligaSetCode": "MEW",
      "tcgdexSetId": "sv03.5",
      "number": "178",
      "printedTotal": "165",
      "imageUrl": "https://assets.tcgdex.net/pt/sv/sv03.5/178",
      "types": [],
      "rarity": ""
    },
    {
      "id": "sv03.5-179",
      "name": "Mr. Mime",
      "searchName": "Mr. Mime",
      "collectionId": "sv03.5",
      "collectionName": "151",
      "ligaSetCode": "MEW",
      "tcgdexSetId": "sv03.5",
      "number": "179",
      "printedTotal": "165",
      "imageUrl": "https://assets.tcgdex.net/pt/sv/sv03.5/179",
      "types": [],
      "rarity": ""
    },
    {
      "id": "sv03.5-180",
      "name": "Omanyte",
      "searchName": "Omanyte",
      "collectionId": "sv03.5",
      "collectionName": "151",
      "ligaSetCode": "MEW",
      "tcgdexSetId": "sv03.5",
      "number": "180",
      "printedTotal": "165",
      "imageUrl": "https://assets.tcgdex.net/pt/sv/sv03.5/180",
      "types": [],
      "rarity": ""
    },
    {
      "id": "sv03.5-181",
      "name": "Dragonair",
      "searchName": "Dragonair",
      "collectionId": "sv03.5",
      "collectionName": "151",
      "ligaSetCode": "MEW",
      "tcgdexSetId": "sv03.5",
      "number": "181",
      "printedTotal": "165",
      "imageUrl": "https://assets.tcgdex.net/pt/sv/sv03.5/181",
      "types": [],
      "rarity": ""
    },
    {
      "id": "sv03.5-182",
      "name": "Venusaur ex",
      "searchName": "Venusaur ex",
      "collectionId": "sv03.5",
      "collectionName": "151",
      "ligaSetCode": "MEW",
      "tcgdexSetId": "sv03.5",
      "number": "182",
      "printedTotal": "165",
      "imageUrl": "https://assets.tcgdex.net/pt/sv/sv03.5/182",
      "types": [],
      "rarity": ""
    },
    {
      "id": "sv03.5-183",
      "name": "Charizard ex",
      "searchName": "Charizard ex",
      "collectionId": "sv03.5",
      "collectionName": "151",
      "ligaSetCode": "MEW",
      "tcgdexSetId": "sv03.5",
      "number": "183",
      "printedTotal": "165",
      "imageUrl": "https://assets.tcgdex.net/pt/sv/sv03.5/183",
      "types": [],
      "rarity": ""
    },
    {
      "id": "sv03.5-184",
      "name": "Blastoise ex",
      "searchName": "Blastoise ex",
      "collectionId": "sv03.5",
      "collectionName": "151",
      "ligaSetCode": "MEW",
      "tcgdexSetId": "sv03.5",
      "number": "184",
      "printedTotal": "165",
      "imageUrl": "https://assets.tcgdex.net/pt/sv/sv03.5/184",
      "types": [],
      "rarity": ""
    },
    {
      "id": "sv03.5-185",
      "name": "Arbok ex",
      "searchName": "Arbok ex",
      "collectionId": "sv03.5",
      "collectionName": "151",
      "ligaSetCode": "MEW",
      "tcgdexSetId": "sv03.5",
      "number": "185",
      "printedTotal": "165",
      "imageUrl": "https://assets.tcgdex.net/pt/sv/sv03.5/185",
      "types": [],
      "rarity": ""
    },
    {
      "id": "sv03.5-186",
      "name": "Ninetales ex",
      "searchName": "Ninetales ex",
      "collectionId": "sv03.5",
      "collectionName": "151",
      "ligaSetCode": "MEW",
      "tcgdexSetId": "sv03.5",
      "number": "186",
      "printedTotal": "165",
      "imageUrl": "https://assets.tcgdex.net/pt/sv/sv03.5/186",
      "types": [],
      "rarity": ""
    },
    {
      "id": "sv03.5-187",
      "name": "Wigglytuff ex",
      "searchName": "Wigglytuff ex",
      "collectionId": "sv03.5",
      "collectionName": "151",
      "ligaSetCode": "MEW",
      "tcgdexSetId": "sv03.5",
      "number": "187",
      "printedTotal": "165",
      "imageUrl": "https://assets.tcgdex.net/pt/sv/sv03.5/187",
      "types": [],
      "rarity": ""
    },
    {
      "id": "sv03.5-188",
      "name": "Alakazam ex",
      "searchName": "Alakazam ex",
      "collectionId": "sv03.5",
      "collectionName": "151",
      "ligaSetCode": "MEW",
      "tcgdexSetId": "sv03.5",
      "number": "188",
      "printedTotal": "165",
      "imageUrl": "https://assets.tcgdex.net/pt/sv/sv03.5/188",
      "types": [],
      "rarity": ""
    },
    {
      "id": "sv03.5-189",
      "name": "Golem ex",
      "searchName": "Golem ex",
      "collectionId": "sv03.5",
      "collectionName": "151",
      "ligaSetCode": "MEW",
      "tcgdexSetId": "sv03.5",
      "number": "189",
      "printedTotal": "165",
      "imageUrl": "https://assets.tcgdex.net/pt/sv/sv03.5/189",
      "types": [],
      "rarity": ""
    },
    {
      "id": "sv03.5-190",
      "name": "Kangaskhan ex",
      "searchName": "Kangaskhan ex",
      "collectionId": "sv03.5",
      "collectionName": "151",
      "ligaSetCode": "MEW",
      "tcgdexSetId": "sv03.5",
      "number": "190",
      "printedTotal": "165",
      "imageUrl": "https://assets.tcgdex.net/pt/sv/sv03.5/190",
      "types": [],
      "rarity": ""
    },
    {
      "id": "sv03.5-191",
      "name": "Jynx ex",
      "searchName": "Jynx ex",
      "collectionId": "sv03.5",
      "collectionName": "151",
      "ligaSetCode": "MEW",
      "tcgdexSetId": "sv03.5",
      "number": "191",
      "printedTotal": "165",
      "imageUrl": "https://assets.tcgdex.net/pt/sv/sv03.5/191",
      "types": [],
      "rarity": ""
    },
    {
      "id": "sv03.5-192",
      "name": "Zapdos ex",
      "searchName": "Zapdos ex",
      "collectionId": "sv03.5",
      "collectionName": "151",
      "ligaSetCode": "MEW",
      "tcgdexSetId": "sv03.5",
      "number": "192",
      "printedTotal": "165",
      "imageUrl": "https://assets.tcgdex.net/pt/sv/sv03.5/192",
      "types": [],
      "rarity": ""
    },
    {
      "id": "sv03.5-193",
      "name": "Mew ex",
      "searchName": "Mew ex",
      "collectionId": "sv03.5",
      "collectionName": "151",
      "ligaSetCode": "MEW",
      "tcgdexSetId": "sv03.5",
      "number": "193",
      "printedTotal": "165",
      "imageUrl": "https://assets.tcgdex.net/pt/sv/sv03.5/193",
      "types": [],
      "rarity": ""
    },
    {
      "id": "sv03.5-194",
      "name": "Transferência do Bill",
      "searchName": "Transferência do Bill",
      "collectionId": "sv03.5",
      "collectionName": "151",
      "ligaSetCode": "MEW",
      "tcgdexSetId": "sv03.5",
      "number": "194",
      "printedTotal": "165",
      "imageUrl": "https://assets.tcgdex.net/pt/sv/sv03.5/194",
      "types": [],
      "rarity": ""
    },
    {
      "id": "sv03.5-195",
      "name": "Ajuda da Daisy",
      "searchName": "Ajuda da Daisy",
      "collectionId": "sv03.5",
      "collectionName": "151",
      "ligaSetCode": "MEW",
      "tcgdexSetId": "sv03.5",
      "number": "195",
      "printedTotal": "165",
      "imageUrl": "https://assets.tcgdex.net/pt/sv/sv03.5/195",
      "types": [],
      "rarity": ""
    },
    {
      "id": "sv03.5-196",
      "name": "Convite da Érica",
      "searchName": "Convite da Érica",
      "collectionId": "sv03.5",
      "collectionName": "151",
      "ligaSetCode": "MEW",
      "tcgdexSetId": "sv03.5",
      "number": "196",
      "printedTotal": "165",
      "imageUrl": "https://assets.tcgdex.net/pt/sv/sv03.5/196",
      "types": [],
      "rarity": ""
    },
    {
      "id": "sv03.5-197",
      "name": "Carisma do Giovanni",
      "searchName": "Carisma do Giovanni",
      "collectionId": "sv03.5",
      "collectionName": "151",
      "ligaSetCode": "MEW",
      "tcgdexSetId": "sv03.5",
      "number": "197",
      "printedTotal": "165",
      "imageUrl": "https://assets.tcgdex.net/pt/sv/sv03.5/197",
      "types": [],
      "rarity": ""
    },
    {
      "id": "sv03.5-198",
      "name": "Venusaur ex",
      "searchName": "Venusaur ex",
      "collectionId": "sv03.5",
      "collectionName": "151",
      "ligaSetCode": "MEW",
      "tcgdexSetId": "sv03.5",
      "number": "198",
      "printedTotal": "165",
      "imageUrl": "https://assets.tcgdex.net/pt/sv/sv03.5/198",
      "types": [],
      "rarity": ""
    },
    {
      "id": "sv03.5-199",
      "name": "Charizard ex",
      "searchName": "Charizard ex",
      "collectionId": "sv03.5",
      "collectionName": "151",
      "ligaSetCode": "MEW",
      "tcgdexSetId": "sv03.5",
      "number": "199",
      "printedTotal": "165",
      "imageUrl": "https://assets.tcgdex.net/pt/sv/sv03.5/199",
      "types": [],
      "rarity": ""
    },
    {
      "id": "sv03.5-200",
      "name": "Blastoise ex",
      "searchName": "Blastoise ex",
      "collectionId": "sv03.5",
      "collectionName": "151",
      "ligaSetCode": "MEW",
      "tcgdexSetId": "sv03.5",
      "number": "200",
      "printedTotal": "165",
      "imageUrl": "https://assets.tcgdex.net/pt/sv/sv03.5/200",
      "types": [],
      "rarity": ""
    },
    {
      "id": "sv03.5-201",
      "name": "Alakazam ex",
      "searchName": "Alakazam ex",
      "collectionId": "sv03.5",
      "collectionName": "151",
      "ligaSetCode": "MEW",
      "tcgdexSetId": "sv03.5",
      "number": "201",
      "printedTotal": "165",
      "imageUrl": "https://assets.tcgdex.net/pt/sv/sv03.5/201",
      "types": [],
      "rarity": ""
    },
    {
      "id": "sv03.5-202",
      "name": "Zapdos ex",
      "searchName": "Zapdos ex",
      "collectionId": "sv03.5",
      "collectionName": "151",
      "ligaSetCode": "MEW",
      "tcgdexSetId": "sv03.5",
      "number": "202",
      "printedTotal": "165",
      "imageUrl": "https://assets.tcgdex.net/pt/sv/sv03.5/202",
      "types": [],
      "rarity": ""
    },
    {
      "id": "sv03.5-203",
      "name": "Convite da Érica",
      "searchName": "Convite da Érica",
      "collectionId": "sv03.5",
      "collectionName": "151",
      "ligaSetCode": "MEW",
      "tcgdexSetId": "sv03.5",
      "number": "203",
      "printedTotal": "165",
      "imageUrl": "https://assets.tcgdex.net/pt/sv/sv03.5/203",
      "types": [],
      "rarity": ""
    },
    {
      "id": "sv03.5-204",
      "name": "Carisma do Giovanni",
      "searchName": "Carisma do Giovanni",
      "collectionId": "sv03.5",
      "collectionName": "151",
      "ligaSetCode": "MEW",
      "tcgdexSetId": "sv03.5",
      "number": "204",
      "printedTotal": "165",
      "imageUrl": "https://assets.tcgdex.net/pt/sv/sv03.5/204",
      "types": [],
      "rarity": ""
    },
    {
      "id": "sv03.5-205",
      "name": "Mew ex",
      "searchName": "Mew ex",
      "collectionId": "sv03.5",
      "collectionName": "151",
      "ligaSetCode": "MEW",
      "tcgdexSetId": "sv03.5",
      "number": "205",
      "printedTotal": "165",
      "imageUrl": "https://assets.tcgdex.net/pt/sv/sv03.5/205",
      "types": [],
      "rarity": ""
    },
    {
      "id": "sv03.5-206",
      "name": "Substituição",
      "searchName": "Substituição",
      "collectionId": "sv03.5",
      "collectionName": "151",
      "ligaSetCode": "MEW",
      "tcgdexSetId": "sv03.5",
      "number": "206",
      "printedTotal": "165",
      "imageUrl": "https://assets.tcgdex.net/pt/sv/sv03.5/206",
      "types": [],
      "rarity": ""
    },
    {
      "id": "sv03.5-207",
      "name": "Energia Psychic Básica",
      "searchName": "Energia Psychic Básica",
      "collectionId": "sv03.5",
      "collectionName": "151",
      "ligaSetCode": "MEW",
      "tcgdexSetId": "sv03.5",
      "number": "207",
      "printedTotal": "165",
      "imageUrl": "https://assets.tcgdex.net/pt/sv/sv03.5/207",
      "types": [],
      "rarity": ""
    }
  ]
}
