{
  "id": "tk-sm-l",
  "name": "SM trainer Kit (Lycanroc)",
  "shortName": "SM trainer Kit (Lycanroc)",
  "serie": "Trainer kits",
  "releaseYear": 2017,
  "releaseDate": "2017-04-21",
  "cardCount": 30,
  "officialCount": 30,
  "ligaSetCode": "TK10L",
  "tcgdexSetId": "tk-sm-l",
  "symbolUrl": "https://assets.tcgdex.net/univ/tk/tk-sm-l/symbol",
  "language": "en",
  "hasPortugueseData": false,
  "cards": [
    {
      "id": "tk-sm-l-1",
      "name": "Caterpie",
      "searchName": "Caterpie",
      "collectionId": "tk-sm-l",
      "collectionName": "SM trainer Kit (Lycanroc)",
      "ligaSetCode": "TK10L",
      "tcgdexSetId": "tk-sm-l",
      "number": "1",
      "printedTotal": "30",
      "types": [],
      "rarity": ""
    },
    {
      "id": "tk-sm-l-4",
      "name": "Trumbeak",
      "searchName": "Trumbeak",
      "collectionId": "tk-sm-l",
      "collectionName": "SM trainer Kit (Lycanroc)",
      "ligaSetCode": "TK10L",
      "tcgdexSetId": "tk-sm-l",
      "number": "4",
      "printedTotal": "30",
      "types": [],
      "rarity": ""
    },
    {
      "id": "tk-sm-l-5",
      "name": "Fighting Energy",
      "searchName": "Fighting Energy",
      "collectionId": "tk-sm-l",
      "collectionName": "SM trainer Kit (Lycanroc)",
      "ligaSetCode": "TK10L",
      "tcgdexSetId": "tk-sm-l",
      "number": "5",
      "printedTotal": "30",
      "types": [],
      "rarity": ""
    },
    {
      "id": "tk-sm-l-11",
      "name": "Fletchling",
      "searchName": "Fletchling",
      "collectionId": "tk-sm-l",
      "collectionName": "SM trainer Kit (Lycanroc)",
      "ligaSetCode": "TK10L",
      "tcgdexSetId": "tk-sm-l",
      "number": "11",
      "printedTotal": "30",
      "types": [],
      "rarity": ""
    },
    {
      "id": "tk-sm-l-12",
      "name": "Yungoos",
      "searchName": "Yungoos",
      "collectionId": "tk-sm-l",
      "collectionName": "SM trainer Kit (Lycanroc)",
      "ligaSetCode": "TK10L",
      "tcgdexSetId": "tk-sm-l",
      "number": "12",
      "printedTotal": "30",
      "types": [],
      "rarity": ""
    },
    {
      "id": "tk-sm-l-13",
      "name": "Fletchinder",
      "searchName": "Fletchinder",
      "collectionId": "tk-sm-l",
      "collectionName": "SM trainer Kit (Lycanroc)",
      "ligaSetCode": "TK10L",
      "tcgdexSetId": "tk-sm-l",
      "number": "13",
      "printedTotal": "30",
      "types": [],
      "rarity": ""
    },
    {
      "id": "tk-sm-l-14",
      "name": "Rockruff",
      "searchName": "Rockruff",
      "collectionId": "tk-sm-l",
      "collectionName": "SM trainer Kit (Lycanroc)",
      "ligaSetCode": "TK10L",
      "tcgdexSetId": "tk-sm-l",
      "number": "14",
      "printedTotal": "30",
      "types": [],
      "rarity": ""
    },
    {
      "id": "tk-sm-l-15",
      "name": "Pikipek",
      "searchName": "Pikipek",
      "collectionId": "tk-sm-l",
      "collectionName": "SM trainer Kit (Lycanroc)",
      "ligaSetCode": "TK10L",
      "tcgdexSetId": "tk-sm-l",
      "number": "15",
      "printedTotal": "30",
      "types": [],
      "rarity": ""
    },
    {
      "id": "tk-sm-l-16",
      "name": "Lycanroc",
      "searchName": "Lycanroc",
      "collectionId": "tk-sm-l",
      "collectionName": "SM trainer Kit (Lycanroc)",
      "ligaSetCode": "TK10L",
      "tcgdexSetId": "tk-sm-l",
      "number": "16",
      "printedTotal": "30",
      "types": [],
      "rarity": ""
    },
    {
      "id": "tk-sm-l-18",
      "name": "Makuhita",
      "searchName": "Makuhita",
      "collectionId": "tk-sm-l",
      "collectionName": "SM trainer Kit (Lycanroc)",
      "ligaSetCode": "TK10L",
      "tcgdexSetId": "tk-sm-l",
      "number": "18",
      "printedTotal": "30",
      "types": [],
      "rarity": ""
    },
    {
      "id": "tk-sm-l-19",
      "name": "Hau",
      "searchName": "Hau",
      "collectionId": "tk-sm-l",
      "collectionName": "SM trainer Kit (Lycanroc)",
      "ligaSetCode": "TK10L",
      "tcgdexSetId": "tk-sm-l",
      "number": "19",
      "printedTotal": "30",
      "types": [],
      "rarity": ""
    },
    {
      "id": "tk-sm-l-21",
      "name": "Great Ball",
      "searchName": "Great Ball",
      "collectionId": "tk-sm-l",
      "collectionName": "SM trainer Kit (Lycanroc)",
      "ligaSetCode": "TK10L",
      "tcgdexSetId": "tk-sm-l",
      "number": "21",
      "printedTotal": "30",
      "types": [],
      "rarity": ""
    },
    {
      "id": "tk-sm-l-22",
      "name": "Toucannon",
      "searchName": "Toucannon",
      "collectionId": "tk-sm-l",
      "collectionName": "SM trainer Kit (Lycanroc)",
      "ligaSetCode": "TK10L",
      "tcgdexSetId": "tk-sm-l",
      "number": "22",
      "printedTotal": "30",
      "types": [],
      "rarity": ""
    },
    {
      "id": "tk-sm-l-23",
      "name": "Hau",
      "searchName": "Hau",
      "collectionId": "tk-sm-l",
      "collectionName": "SM trainer Kit (Lycanroc)",
      "ligaSetCode": "TK10L",
      "tcgdexSetId": "tk-sm-l",
      "number": "23",
      "printedTotal": "30",
      "types": [],
      "rarity": ""
    },
    {
      "id": "tk-sm-l-25",
      "name": "Great Ball",
      "searchName": "Great Ball",
      "collectionId": "tk-sm-l",
      "collectionName": "SM trainer Kit (Lycanroc)",
      "ligaSetCode": "TK10L",
      "tcgdexSetId": "tk-sm-l",
      "number": "25",
      "printedTotal": "30",
      "types": [],
      "rarity": ""
    },
    {
      "id": "tk-sm-l-27",
      "name": "Big Malasada",
      "searchName": "Big Malasada",
      "collectionId": "tk-sm-l",
      "collectionName": "SM trainer Kit (Lycanroc)",
      "ligaSetCode": "TK10L",
      "tcgdexSetId": "tk-sm-l",
      "number": "27",
      "printedTotal": "30",
      "types": [],
      "rarity": ""
    },
    {
      "id": "tk-sm-l-29",
      "name": "Rockruff",
      "searchName": "Rockruff",
      "collectionId": "tk-sm-l",
      "collectionName": "SM trainer Kit (Lycanroc)",
      "ligaSetCode": "TK10L",
      "tcgdexSetId": "tk-sm-l",
      "number": "29",
      "printedTotal": "30",
      "types": [],
      "rarity": ""
    },
    {
      "id": "tk-sm-l-30",
      "name": "Lycanroc",
      "searchName": "Lycanroc",
      "collectionId": "tk-sm-l",
      "collectionName": "SM trainer Kit (Lycanroc)",
      "ligaSetCode": "TK10L",
      "tcgdexSetId": "tk-sm-l",
      "number": "30",
      "printedTotal": "30",
      "types": [],
      "rarity": ""
    }
  ]
}
